LMS.v
// LMS_core.v
module LMS_core (
    input              Clk,
    input              Rst,
    input  signed [15:0] x_in,      // Input sample (Q4.12)
    input  signed [15:0] d_in,      // Desired sample (Q4.12)
    input              training_en, // 1: update weights, 0: freeze
    input  signed [15:0] gamma,     // Step size (Q4.12)
    input  signed [15:0] w0_set,    // External write values (used when load_weights=1)
    input  signed [15:0] w1_set,
    input  signed [15:0] w2_set,
    input  signed [15:0] w3_set,
    input              load_weights, // Pulse: load w*_set into wn[*]
    output signed [15:0] y_out,     // Output (Q4.12)
    output signed [15:0] err,       // Error (Q4.12)
    output signed [15:0] w0, w1, w2, w3 // Current weights
);

  // Tap delay line for x
  reg signed [15:0] x[0:3];
  always @(posedge Clk or posedge Rst) begin
    if (Rst) begin
      x[0] <= 16'sd0; x[1] <= 16'sd0; x[2] <= 16'sd0; x[3] <= 16'sd0;
    end else begin
      x[3] <= x[2];
      x[2] <= x[1];
      x[1] <= x[0];
      x[0] <= x_in;
    end
  end

  // Weights
  reg signed [15:0] wn[0:3];
  // Optional external load
  always @(posedge Clk or posedge Rst) begin
    if (Rst) begin
      wn[0] <= 16'sd0; wn[1] <= 16'sd0; wn[2] <= 16'sd0; wn[3] <= 16'sd0;
    end else if (load_weights) begin
      wn[0] <= w0_set; wn[1] <= w1_set; wn[2] <= w2_set; wn[3] <= w3_set;
    end
  end

  // Output y = sum(wn[i]*x[i]) -> Q4.12
  wire signed [31:0] y_acc = $signed(wn[0])*$signed(x[0]) +
                             $signed(wn[1])*$signed(x[1]) +
                             $signed(wn[2])*$signed(x[2]) +
                             $signed(wn[3])*$signed(x[3]);
  assign y_out = y_acc[27:12];

  // Error
  assign err = d_in - y_out;

  // LMS updates gated by training_en
  // m_i = gamma * (err * x[i]) with truncations to Q4.12
  wire signed [31:0] p0 = $signed(err) * $signed(x[0]);
  wire signed [15:0] p0_q = p0[27:12];
  wire signed [31:0] a0 = $signed(gamma) * $signed(p0_q);
  wire signed [15:0] a0_q = a0[27:12];

  wire signed [31:0] p1 = $signed(err) * $signed(x[1]);
  wire signed [15:0] p1_q = p1[27:12];
  wire signed [31:0] a1 = $signed(gamma) * $signed(p1_q);
  wire signed [15:0] a1_q = a1[27:12];

  wire signed [31:0] p2 = $signed(err) * $signed(x[2]);
  wire signed [15:0] p2_q = p2[27:12];
  wire signed [31:0] a2 = $signed(gamma) * $signed(p2_q);
  wire signed [15:0] a2_q = a2[27:12];

  wire signed [31:0] p3 = $signed(err) * $signed(x[3]);
  wire signed [15:0] p3_q = p3[27:12];
  wire signed [31:0] a3 = $signed(gamma) * $signed(p3_q);
  wire signed [15:0] a3_q = a3[27:12];

  wire signed [15:0] wn_u0 = wn[0] + a0_q;
  wire signed [15:0] wn_u1 = wn[1] + a1_q;
  wire signed [15:0] wn_u2 = wn[2] + a2_q;
  wire signed [15:0] wn_u3 = wn[3] + a3_q;

  always @(posedge Clk or posedge Rst) begin
    if (Rst) begin
      // already reset above
    end else if (training_en) begin
      wn[0] <= wn_u0;
      wn[1] <= wn_u1;
      wn[2] <= wn_u2;
      wn[3] <= wn_u3;
    end
  end

  assign w0 = wn[0];
  assign w1 = wn[1];
  assign w2 = wn[2];
  assign w3 = wn[3];

endmodule

wb_lms.v
module wb_lms #(
  parameter FIFO_DEPTH = 256
)(
  input  wire        Clk,
  input  wire        Rst,
  input  wire        wb_cyc_i,
  input  wire        wb_stb_i,
  input  wire        wb_we_i,
  input  wire [31:0] wb_adr_i,
  input  wire [15:0] wb_dat_i,
  output reg  [15:0] wb_dat_o,
  output reg         wb_ack_o,
  output reg         irq_o,

  // Debug outputs
  output wire [15:0] dbg_x_in,
  output wire [15:0] dbg_d_in,
  output wire [15:0] dbg_y_out,
  output wire [15:0] dbg_err,
  output wire [15:0] dbg_w0,
  output wire [15:0] dbg_w1,
  output wire [15:0] dbg_w2,
  output wire [15:0] dbg_w3
);

  reg [15:0] x_in_reg, d_in_reg;
  wire [15:0] y_out, err;
  wire [15:0] w0, w1, w2, w3;

  LMS_core core (
    .Clk(Clk),
    .Rst(Rst),
    .x_in(x_in_reg),
    .d_in(d_in_reg),
    .y_out(y_out),
    .err(err),
    .w0(w0), .w1(w1), .w2(w2), .w3(w3)
  );

  always @(posedge Clk) begin
    if (Rst) begin
      wb_ack_o <= 0;
      wb_dat_o <= 0;
      x_in_reg <= 0;
      d_in_reg <= 0;
      irq_o    <= 0;
    end else begin
      wb_ack_o <= 0;
      irq_o    <= 0;
      if (wb_cyc_i && wb_stb_i && !wb_ack_o) begin
        wb_ack_o <= 1;
        if (wb_we_i) begin
          case (wb_adr_i[5:2])
            4'h3: x_in_reg <= wb_dat_i;
            4'h4: d_in_reg <= wb_dat_i;
          endcase
          irq_o <= 1;
        end else begin
          case (wb_adr_i[5:2])
            4'h3: wb_dat_o <= y_out;
            4'h4: wb_dat_o <= err;
          endcase
        end
      end
    end
  end

  assign dbg_x_in  = x_in_reg;
  assign dbg_d_in  = d_in_reg;
  assign dbg_y_out = y_out;
  assign dbg_err   = err;
  assign dbg_w0    = w0;
  assign dbg_w1    = w1;
  assign dbg_w2    = w2;
  assign dbg_w3    = w3;

endmodule

wb_lms_tb.v
`timescale 1ns/1ps
module wb_lms_tb;
  reg Clk, Rst;
  reg         wb_cyc_i, wb_stb_i, wb_we_i;
  reg  [31:0] wb_adr_i;
  reg  [15:0] wb_dat_i;
  wire [15:0] wb_dat_o;
  wire        wb_ack_o;
  wire        irq_o;

  reg signed [15:0] x_vec [0:99];
  reg signed [15:0] d_vec [0:99];
  integer i, csv_fd;
  localparam SF = 2.0**-12.0;

  wb_lms #(.FIFO_DEPTH(256)) dut (
    .Clk(Clk), .Rst(Rst),
    .wb_cyc_i(wb_cyc_i), .wb_stb_i(wb_stb_i), .wb_we_i(wb_we_i),
    .wb_adr_i(wb_adr_i), .wb_dat_i(wb_dat_i),
    .wb_dat_o(wb_dat_o), .wb_ack_o(wb_ack_o),
    .irq_o(irq_o),
    .dbg_x_in(), .dbg_d_in(), .dbg_y_out(), .dbg_err(),
    .dbg_w0(), .dbg_w1(), .dbg_w2(), .dbg_w3()
  );

  always #5 Clk = ~Clk;

  task wb_write;
    input [31:0] addr;
    input [15:0] data;
    begin
      @(negedge Clk);
      wb_adr_i = addr;
      wb_dat_i = data;
      wb_we_i  = 1;
      wb_cyc_i = 1;
      wb_stb_i = 1;
      @(posedge Clk);
      while (!wb_ack_o) @(posedge Clk);
      @(negedge Clk);
      wb_cyc_i = 0;
      wb_stb_i = 0;
      wb_we_i  = 0;
    end
  endtask

  task log_csv;
    input integer fd;
    input integer idx;
    reg signed [15:0] x, d, y, e, w0, w1, w2, w3;
    begin
      x  = dut.dbg_x_in;
      d  = dut.dbg_d_in;
      y  = dut.dbg_y_out;
      e  = dut.dbg_err;
      w0 = dut.dbg_w0;
      w1 = dut.dbg_w1;
      w2 = dut.dbg_w2;
      w3 = dut.dbg_w3;
      $fwrite(fd, "%0t,%0d,%f,%f,%f,%f,%f,%f,%f,%f\n",
        $time, idx,
        $itor(x)*SF, $itor(d)*SF, $itor(y)*SF, $itor(e)*SF,
        $itor(w0)*SF, $itor(w1)*SF, $itor(w2)*SF, $itor(w3)*SF
      );
    end
  endtask

  initial begin
    Clk = 0; Rst = 1;
    wb_cyc_i = 0; wb_stb_i = 0; wb_we_i = 0; wb_adr_i = 0; wb_dat_i = 0;
    repeat(2) @(negedge Clk);
    Rst = 0;

    $readmemb("LMS_inputs.txt", x_vec);
    $readmemb("LMS_expected.txt", d_vec);

    csv_fd = $fopen("lms_log.csv", "w");
    $fwrite(csv_fd, "time_ns,index,x,d,y,err,w0,w1,w2,w3\n");

    wb_write(32'h08, 16'b0000001100110011); // gamma
    wb_write(32'h00, 16'h0008); // clear

    for (i=0; i<100; i=i+1) begin
      wb_write(32'h0C, x_vec[i]);
      wb_write(32'h10, d_vec[i]);
    end

    wb_write(32'h00, 16'h0005); // enable training

    for (i=0; i<100; i=i+1) begin
      @(posedge Clk);
      log_csv(csv_fd, i);
    end

    wb_write(32'h00, 16'h0004); // disable training
    wb_write(32'h00, 16'h0008); // clear

    for (i=0; i<100; i=i+1) begin
      wb_write(32'h0C, x_vec[i]);
    end

    for (i=0; i<100; i=i+1) begin
      @(posedge Clk);
      log_csv(csv_fd, i+100);
    end

    $fclose(csv_fd);
    repeat(20) @(negedge Clk);
    $finish;
  end

  initial begin
    $dumpfile("dump_wb_lms.vcd");
    $dumpvars(0, wb_lms_tb);
  end
endmodule

dump_wb_lms.vcd
$date
	Fri Oct 24 23:20:24 2025
$end
$version
	Icarus Verilog
$end
$timescale
	1ps
$end
$scope module wb_lms_tb $end
$var wire 16 ! wb_dat_o [15:0] $end
$var wire 1 " wb_ack_o $end
$var wire 1 # irq_o $end
$var real 1 $ SF $end
$var reg 1 % Clk $end
$var reg 1 & Rst $end
$var reg 32 ' wb_adr_i [31:0] $end
$var reg 1 ( wb_cyc_i $end
$var reg 16 ) wb_dat_i [15:0] $end
$var reg 1 * wb_stb_i $end
$var reg 1 + wb_we_i $end
$var integer 32 , csv_fd [31:0] $end
$var integer 32 - i [31:0] $end
$scope module dut $end
$var wire 1 % Clk $end
$var wire 1 & Rst $end
$var wire 16 . dbg_d_in [15:0] $end
$var wire 16 / dbg_err [15:0] $end
$var wire 16 0 dbg_w0 [15:0] $end
$var wire 16 1 dbg_w1 [15:0] $end
$var wire 16 2 dbg_w2 [15:0] $end
$var wire 16 3 dbg_w3 [15:0] $end
$var wire 16 4 dbg_x_in [15:0] $end
$var wire 16 5 dbg_y_out [15:0] $end
$var wire 32 6 wb_adr_i [31:0] $end
$var wire 1 ( wb_cyc_i $end
$var wire 16 7 wb_dat_i [15:0] $end
$var wire 1 * wb_stb_i $end
$var wire 1 + wb_we_i $end
$var wire 16 8 y_out [15:0] $end
$var wire 16 9 w3 [15:0] $end
$var wire 16 : w2 [15:0] $end
$var wire 16 ; w1 [15:0] $end
$var wire 16 < w0 [15:0] $end
$var wire 16 = err [15:0] $end
$var parameter 32 > FIFO_DEPTH $end
$var reg 16 ? d_in_reg [15:0] $end
$var reg 1 # irq_o $end
$var reg 1 " wb_ack_o $end
$var reg 16 @ wb_dat_o [15:0] $end
$var reg 16 A x_in_reg [15:0] $end
$scope module core $end
$var wire 1 % Clk $end
$var wire 1 & Rst $end
$var wire 16 B d_in [15:0] $end
$var wire 16 C gamma [15:0] $end
$var wire 1 D load_weights $end
$var wire 1 E training_en $end
$var wire 16 F w0 [15:0] $end
$var wire 16 G w0_set [15:0] $end
$var wire 16 H w1 [15:0] $end
$var wire 16 I w1_set [15:0] $end
$var wire 16 J w2 [15:0] $end
$var wire 16 K w2_set [15:0] $end
$var wire 16 L w3 [15:0] $end
$var wire 16 M w3_set [15:0] $end
$var wire 16 N x_in [15:0] $end
$var wire 16 O y_out [15:0] $end
$var wire 32 P y_acc [31:0] $end
$var wire 16 Q wn_u3 [15:0] $end
$var wire 16 R wn_u2 [15:0] $end
$var wire 16 S wn_u1 [15:0] $end
$var wire 16 T wn_u0 [15:0] $end
$var wire 16 U p3_q [15:0] $end
$var wire 32 V p3 [31:0] $end
$var wire 16 W p2_q [15:0] $end
$var wire 32 X p2 [31:0] $end
$var wire 16 Y p1_q [15:0] $end
$var wire 32 Z p1 [31:0] $end
$var wire 16 [ p0_q [15:0] $end
$var wire 32 \ p0 [31:0] $end
$var wire 16 ] err [15:0] $end
$var wire 16 ^ a3_q [15:0] $end
$var wire 32 _ a3 [31:0] $end
$var wire 16 ` a2_q [15:0] $end
$var wire 32 a a2 [31:0] $end
$var wire 16 b a1_q [15:0] $end
$var wire 32 c a1 [31:0] $end
$var wire 16 d a0_q [15:0] $end
$var wire 32 e a0 [31:0] $end
$upscope $end
$upscope $end
$scope task log_csv $end
$var reg 16 f d [15:0] $end
$var reg 16 g e [15:0] $end
$var reg 16 h w0 [15:0] $end
$var reg 16 i w1 [15:0] $end
$var reg 16 j w2 [15:0] $end
$var reg 16 k w3 [15:0] $end
$var reg 16 l x [15:0] $end
$var reg 16 m y [15:0] $end
$var integer 32 n fd [31:0] $end
$var integer 32 o idx [31:0] $end
$upscope $end
$scope task wb_write $end
$var reg 32 p addr [31:0] $end
$var reg 16 q data [15:0] $end
$upscope $end
$upscope $end
$enddefinitions $end
$comment Show the parameter values. $end
$dumpall
b100000000 >
r0.000244140625 $
$end
#0
$dumpvars
bx q
bx p
bx o
bx n
bx m
bx l
bx k
bx j
bx i
bx h
bx g
bx f
bx e
bx d
bx c
bx b
bx a
bx `
bx _
bx ^
bx ]
bx \
bx [
bx Z
bx Y
bx X
bx W
bx V
bx U
bx T
bx S
bx R
bx Q
b0 P
b0 O
bx N
bz M
b0 L
bz K
b0 J
bz I
b0 H
bz G
b0 F
zE
zD
bz C
bx B
bx A
bx @
bx ?
bx =
b0 <
b0 ;
b0 :
b0 9
b0 8
b0 7
b0 6
b0 5
bx 4
b0 3
b0 2
b0 1
b0 0
bx /
bx .
bx -
bx ,
0+
0*
b0 )
0(
b0 '
1&
0%
x#
x"
bx !
$end
#5000
b0 [
b0 Y
b0 W
b0 U
0#
b0 \
b0 Z
b0 X
b0 V
b0 /
b0 =
b0 ]
b0 .
b0 ?
b0 B
b0 4
b0 A
b0 N
b0 !
b0 @
0"
1%
#10000
0%
#15000
1%
#20000
b1100110011 q
b1000 p
b10000000000000000000000000000011 ,
0&
0%
#25000
1%
#30000
1*
1(
1+
b1100110011 )
b1100110011 7
b1000 '
b1000 6
0%
#35000
1#
1"
1%
#40000
0%
#45000
0#
0"
1%
#50000
b1000 q
b0 p
0+
0*
0(
0%
#55000
1%
#60000
1*
1(
1+
b1000 )
b1000 7
b0 '
b0 6
0%
#65000
1#
1"
1%
#70000
0%
#75000
0#
0"
1%
#80000
b1111101111010101 q
b1100 p
b0 -
0+
0*
0(
0%
#85000
1%
#90000
1*
1(
1+
b1111101111010101 )
b1111101111010101 7
b1100 '
b1100 6
0%
#95000
1#
b1111101111010101 4
b1111101111010101 A
b1111101111010101 N
1"
1%
#100000
0%
#105000
0#
0"
1%
#110000
b0 q
b10000 p
0+
0*
0(
0%
#115000
1%
#120000
1*
1(
1+
b0 )
b0 7
b10000 '
b10000 6
0%
#125000
1#
1"
1%
#130000
0%
#135000
0#
0"
1%
#140000
b1111101110010010 q
b1100 p
b1 -
0+
0*
0(
0%
#145000
1%
#150000
1*
1(
1+
b1111101110010010 )
b1111101110010010 7
b1100 '
b1100 6
0%
#155000
1#
b1111101110010010 4
b1111101110010010 A
b1111101110010010 N
1"
1%
#160000
0%
#165000
0#
0"
1%
#170000
b1111011011 q
b10000 p
0+
0*
0(
0%
#175000
1%
#180000
1*
1(
1+
b1111011011 )
b1111011011 7
b10000 '
b10000 6
0%
#185000
b1111111011101110 [
b1111111011101110 Y
b1111111011101110 W
b1111111011111110 U
1#
b11111111111011101110101111100110 \
b11111111111011101110101111100110 Z
b11111111111011101110101111100110 X
b11111111111011111110111000110111 V
b1111011011 /
b1111011011 =
b1111011011 ]
b1111011011 .
b1111011011 ?
b1111011011 B
1"
1%
#190000
0%
#195000
b1111111011101110 U
b11111111111011101110101111100110 V
0#
0"
1%
#200000
b1111111110010000 q
b1100 p
b10 -
0+
0*
0(
0%
#205000
1%
#210000
1*
1(
1+
b1111111110010000 )
b1111111110010000 7
b1100 '
b1100 6
0%
#215000
1#
b1111111110010000 4
b1111111110010000 A
b1111111110010000 N
1"
1%
#220000
0%
#225000
b1111111111100101 [
b11111111111111100101000000110000 \
0#
0"
1%
#230000
b11011000001 q
b10000 p
0+
0*
0(
0%
#235000
b1111111111100101 Y
b11111111111111100101000000110000 Z
1%
#240000
1*
1(
1+
b11011000001 )
b11011000001 7
b10000 '
b10000 6
0%
#245000
b1111111111010000 [
b1111111111010000 Y
b1111111111010000 W
b1111111000100001 U
1#
b11111111111111010000101110010000 \
b11111111111111010000101110010000 Z
b11111111111111010000101110010000 X
b11111111111000100001010100010010 V
b11011000001 /
b11011000001 =
b11011000001 ]
b11011000001 .
b11011000001 ?
b11011000001 B
1"
1%
#250000
0%
#255000
b1111111111010000 U
b11111111111111010000101110010000 V
0#
0"
1%
#260000
b11001100100 q
b1100 p
b11 -
0+
0*
0(
0%
#265000
1%
#270000
1*
1(
1+
b11001100100 )
b11001100100 7
b1100 '
b1100 6
0%
#275000
1#
b11001100100 4
b11001100100 A
b11001100100 N
1"
1%
#280000
0%
#285000
b1010110010 [
b1010110010100101100100 \
0#
0"
1%
#290000
b11111111100 q
b10000 p
0+
0*
0(
0%
#295000
b1010110010 Y
b1010110010100101100100 Z
1%
#300000
1*
1(
1+
b11111111100 )
b11111111100 7
b10000 '
b10000 6
0%
#305000
b1100110000 [
b1100110000 Y
b1100110000 W
b1111111111001000 U
1#
b1100110000011001110000 \
b1100110000011001110000 Z
b1100110000011001110000 X
b11111111111111001000000111000000 V
b11111111100 /
b11111111100 =
b11111111100 ]
b11111111100 .
b11111111100 ?
b11111111100 B
1"
1%
#310000
0%
#315000
b1100110000 U
b1100110000011001110000 V
0#
0"
1%
#320000
b10111011111 q
b1100 p
b100 -
0+
0*
0(
0%
#325000
1%
#330000
1*
1(
1+
b10111011111 )
b10111011111 7
b1100 '
b1100 6
0%
#335000
1#
b10111011111 4
b10111011111 A
b10111011111 N
1"
1%
#340000
0%
#345000
b1011101110 [
b1011101110000010000100 \
0#
0"
1%
#350000
b11100111101 q
b10000 p
0+
0*
0(
0%
#355000
b1011101110 Y
b1011101110000010000100 Z
1%
#360000
1*
1(
1+
b11100111101 )
b11100111101 7
b10000 '
b10000 6
0%
#365000
b1010100111 [
b1010100111 Y
b1010100111 W
b1011100100 U
1#
b1010100111111100100011 \
b1010100111111100100011 Z
b1010100111111100100011 X
b1011100100000111010100 V
b11100111101 /
b11100111101 =
b11100111101 ]
b11100111101 .
b11100111101 ?
b11100111101 B
1"
1%
#370000
0%
#375000
b1010100111 U
b1010100111111100100011 V
0#
0"
1%
#380000
b100000001110 q
b1100 p
b101 -
0+
0*
0(
0%
#385000
1%
#390000
1*
1(
1+
b100000001110 )
b100000001110 7
b1100 '
b1100 6
0%
#395000
1#
b100000001110 4
b100000001110 A
b100000001110 N
1"
1%
#400000
0%
#405000
b1110100100 [
b1110100100110101010110 \
0#
0"
1%
#410000
b10010110100 q
b10000 p
0+
0*
0(
0%
#415000
b1110100100 Y
b1110100100110101010110 Z
1%
#420000
1*
1(
1+
b10010110100 )
b10010110100 7
b10000 '
b10000 6
0%
#425000
b1001011110 [
b1001011110 Y
b1001011110 W
b110111001 U
1#
b1001011110000111011000 \
b1001011110000111011000 Z
b1001011110000111011000 X
b110111001110011001100 V
b10010110100 /
b10010110100 =
b10010110100 ]
b10010110100 .
b10010110100 ?
b10010110100 B
1"
1%
#430000
0%
#435000
b1001011110 U
b1001011110000111011000 V
0#
0"
1%
#440000
b11110111011 q
b1100 p
b110 -
0+
0*
0(
0%
#445000
1%
#450000
1*
1(
1+
b11110111011 )
b11110111011 7
b1100 '
b1100 6
0%
#455000
1#
b11110111011 4
b11110111011 A
b11110111011 N
1"
1%
#460000
0%
#465000
b1001000101 [
b1001000101101101111100 \
0#
0"
1%
#470000
b100000001 q
b10000 p
0+
0*
0(
0%
#475000
b1001000101 Y
b1001000101101101111100 Z
1%
#480000
1*
1(
1+
b100000001 )
b100000001 7
b10000 '
b10000 6
0%
#485000
b1111100 [
b1111100 Y
b1111100 W
b10000001 U
1#
b1111100001010111011 \
b1111100001010111011 Z
b1111100001010111011 X
b10000001011000001110 V
b100000001 /
b100000001 =
b100000001 ]
b100000001 .
b100000001 ?
b100000001 B
1"
1%
#490000
0%
#495000
b1111100 U
b1111100001010111011 V
0#
0"
1%
#500000
b1001001001111 q
b1100 p
b111 -
0+
0*
0(
0%
#505000
1%
#510000
1*
1(
1+
b1001001001111 )
b1001001001111 7
b1100 '
b1100 6
0%
#515000
1#
b1001001001111 4
b1001001001111 A
b1001001001111 N
1"
1%
#520000
0%
#525000
b100100110 [
b100100110000101001111 \
0#
0"
1%
#530000
b1111110100001110 q
b10000 p
0+
0*
0(
0%
#535000
b100100110 Y
b100100110000101001111 Z
1%
#540000
1*
1(
1+
b1111110100001110 )
b1111110100001110 7
b10000 '
b10000 6
0%
#545000
b1111110010100001 [
b1111110010100001 Y
b1111110010100001 W
b1111111010010011 U
1#
b11111111110010100001001101010010 \
b11111111110010100001001101010010 Z
b11111111110010100001001101010010 X
b11111111111010010011101100111010 V
b1111110100001110 /
b1111110100001110 =
b1111110100001110 ]
b1111110100001110 .
b1111110100001110 ?
b1111110100001110 B
1"
1%
#550000
0%
#555000
b1111110010100001 U
b11111111110010100001001101010010 V
0#
0"
1%
#560000
b1111100100101101 q
b1100 p
b1000 -
0+
0*
0(
0%
#565000
1%
#570000
1*
1(
1+
b1111100100101101 )
b1111100100101101 7
b1100 '
b1100 6
0%
#575000
1#
b1111100100101101 4
b1111100100101101 A
b1111100100101101 N
1"
1%
#580000
0%
#585000
b101000001 [
b101000001100101110110 \
0#
0"
1%
#590000
b1111100111010110 q
b10000 p
0+
0*
0(
0%
#595000
b101000001 Y
b101000001100101110110 Z
1%
#600000
1*
1(
1+
b1111100111010110 )
b1111100111010110 7
b10000 '
b10000 6
0%
#605000
b1010100001 [
b1010100001 Y
b1010100001 W
b1111100011110010 U
1#
b1010100001000010011110 \
b1010100001000010011110 Z
b1010100001000010011110 X
b11111111100011110010010100001010 V
b1111100111010110 /
b1111100111010110 =
b1111100111010110 ]
b1111100111010110 .
b1111100111010110 ?
b1111100111010110 B
1"
1%
#610000
0%
#615000
b1010100001 U
b1010100001000010011110 V
0#
0"
1%
#620000
b1111111010001010 q
b1100 p
b1001 -
0+
0*
0(
0%
#625000
1%
#630000
1*
1(
1+
b1111111010001010 )
b1111111010001010 7
b1100 '
b1100 6
0%
#635000
1#
b1111111010001010 4
b1111111010001010 A
b1111111010001010 N
1"
1%
#640000
0%
#645000
b10010000 [
b10010000000101011100 \
0#
0"
1%
#650000
b1111100000100100 q
b10000 p
0+
0*
0(
0%
#655000
b10010000 Y
b10010000000101011100 Z
1%
#660000
1*
1(
1+
b1111100000100100 )
b1111100000100100 7
b10000 '
b10000 6
0%
#665000
b10110111 [
b10110111 Y
b10110111 W
b1101011010 U
1#
b10110111101101101000 \
b10110111101101101000 Z
b10110111101101101000 X
b1101011010001001010100 V
b1111100000100100 /
b1111100000100100 =
b1111100000100100 ]
b1111100000100100 .
b1111100000100100 ?
b1111100000100100 B
1"
1%
#670000
0%
#675000
b10110111 U
b10110111101101101000 V
0#
0"
1%
#680000
b1001010110 q
b1100 p
b1010 -
0+
0*
0(
0%
#685000
1%
#690000
1*
1(
1+
b1001010110 )
b1001010110 7
b1100 '
b1100 6
0%
#695000
1#
b1001010110 4
b1001010110 A
b1001010110 N
1"
1%
#700000
0%
#705000
b1111111011011010 [
b11111111111011011010010000011000 \
0#
0"
1%
#710000
b1111100001100100 q
b10000 p
0+
0*
0(
0%
#715000
b1111111011011010 Y
b11111111111011011010010000011000 Z
1%
#720000
1*
1(
1+
b1111100001100100 )
b1111100001100100 7
b10000 '
b10000 6
0%
#725000
b1111111011100011 [
b1111111011100011 Y
b1111111011100011 W
b10110001 U
1#
b11111111111011100011100110011000 \
b11111111111011100011100110011000 Z
b11111111111011100011100110011000 X
b10110001110111101000 V
b1111100001100100 /
b1111100001100100 =
b1111100001100100 ]
b1111100001100100 .
b1111100001100100 ?
b1111100001100100 B
1"
1%
#730000
0%
#735000
b1111111011100011 U
b11111111111011100011100110011000 V
0#
0"
1%
#740000
b1111010101111011 q
b1100 p
b1011 -
0+
0*
0(
0%
#745000
1%
#750000
1*
1(
1+
b1111010101111011 )
b1111010101111011 7
b1100 '
b1100 6
0%
#755000
1#
b1111010101111011 4
b1111010101111011 A
b1111010101111011 N
1"
1%
#760000
0%
#765000
b10100000000 [
b10100000000110000001100 \
0#
0"
1%
#770000
b1111101010000110 q
b10000 p
0+
0*
0(
0%
#775000
b10100000000 Y
b10100000000110000001100 Z
1%
#780000
1*
1(
1+
b1111101010000110 )
b1111101010000110 7
b10000 '
b10000 6
0%
#785000
b1110011001 [
b1110011001 Y
b1110011001 W
b1111111100110011 U
1#
b1110011001110001100010 \
b1110011001110001100010 Z
b1110011001110001100010 X
b11111111111100110011010100000100 V
b1111101010000110 /
b1111101010000110 =
b1111101010000110 ]
b1111101010000110 .
b1111101010000110 ?
b1111101010000110 B
1"
1%
#790000
0%
#795000
b1110011001 U
b1110011001110001100010 V
0#
0"
1%
#800000
b100111101 q
b1100 p
b1100 -
0+
0*
0(
0%
#805000
1%
#810000
1*
1(
1+
b100111101 )
b100111101 7
b1100 '
b1100 6
0%
#815000
1#
b100111101 4
b100111101 A
b100111101 N
1"
1%
#820000
0%
#825000
b1111111110010011 [
b11111111111110010011011111101110 \
0#
0"
1%
#830000
b1111111000000011 q
b10000 p
0+
0*
0(
0%
#835000
b1111111110010011 Y
b11111111111110010011011111101110 Z
1%
#840000
1*
1(
1+
b1111111000000011 )
b1111111000000011 7
b10000 '
b10000 6
0%
#845000
b1111111111011000 [
b1111111111011000 Y
b1111111111011000 W
b101001110 U
1#
b11111111111111011000100110110111 \
b11111111111111011000100110110111 Z
b11111111111111011000100110110111 X
b101001110101001110001 V
b1111111000000011 /
b1111111000000011 =
b1111111000000011 ]
b1111111000000011 .
b1111111000000011 ?
b1111111000000011 B
1"
1%
#850000
0%
#855000
b1111111111011000 U
b11111111111111011000100110110111 V
0#
0"
1%
#860000
b1100001000 q
b1100 p
b1101 -
0+
0*
0(
0%
#865000
1%
#870000
1*
1(
1+
b1100001000 )
b1100001000 7
b1100 '
b1100 6
0%
#875000
1#
b1100001000 4
b1100001000 A
b1100001000 N
1"
1%
#880000
0%
#885000
b1111111110011111 [
b11111111111110011111100100011000 \
0#
0"
1%
#890000
b111111101 q
b10000 p
0+
0*
0(
0%
#895000
b1111111110011111 Y
b11111111111110011111100100011000 Z
1%
#900000
1*
1(
1+
b111111101 )
b111111101 7
b10000 '
b10000 6
0%
#905000
b1100000 [
b1100000 Y
b1100000 W
b100111 U
1#
b1100000011011101000 \
b1100000011011101000 Z
b1100000011011101000 X
b100111011001001001 V
b111111101 /
b111111101 =
b111111101 ]
b111111101 .
b111111101 ?
b111111101 B
1"
1%
#910000
0%
#915000
b1100000 U
b1100000011011101000 V
0#
0"
1%
#920000
b1111111101110011 q
b1100 p
b1110 -
0+
0*
0(
0%
#925000
1%
#930000
1*
1(
1+
b1111111101110011 )
b1111111101110011 7
b1100 '
b1100 6
0%
#935000
1#
b1111111101110011 4
b1111111101110011 A
b1111111101110011 N
1"
1%
#940000
0%
#945000
b1111111111101110 [
b11111111111111101110011110100111 \
0#
0"
1%
#950000
b10101111010 q
b10000 p
0+
0*
0(
0%
#955000
b1111111111101110 Y
b11111111111111101110011110100111 Z
1%
#960000
1*
1(
1+
b10101111010 )
b10101111010 7
b10000 '
b10000 6
0%
#965000
b1111111111001111 [
b1111111111001111 Y
b1111111111001111 W
b100001001 U
1#
b11111111111111001111101111001110 \
b11111111111111001111101111001110 Z
b11111111111111001111101111001110 X
b100001001100111010000 V
b10101111010 /
b10101111010 =
b10101111010 ]
b10101111010 .
b10101111010 ?
b10101111010 B
1"
1%
#970000
0%
#975000
b1111111111001111 U
b11111111111111001111101111001110 V
0#
0"
1%
#980000
b1100011110 q
b1100 p
b1111 -
0+
0*
0(
0%
#985000
1%
#990000
1*
1(
1+
b1100011110 )
b1100011110 7
b1100 '
b1100 6
0%
#995000
1#
b1100011110 4
b1100011110 A
b1100011110 N
1"
1%
#1000000
0%
#1005000
b100010001 [
b100010001001001001100 \
0#
0"
1%
#1010000
b11110011100 q
b10000 p
0+
0*
0(
0%
#1015000
b100010001 Y
b100010001001001001100 Z
1%
#1020000
1*
1(
1+
b11110011100 )
b11110011100 7
b10000 '
b10000 6
0%
#1025000
b101111011 [
b101111011 Y
b101111011 W
b1111111110111100 U
1#
b101111011100001001000 \
b101111011100001001000 Z
b101111011100001001000 X
b11111111111110111100111100010100 V
b11110011100 /
b11110011100 =
b11110011100 ]
b11110011100 .
b11110011100 ?
b11110011100 B
1"
1%
#1030000
0%
#1035000
b101111011 U
b101111011100001001000 V
0#
0"
1%
#1040000
b1111111001111110 q
b1100 p
b10000 -
0+
0*
0(
0%
#1045000
1%
#1050000
1*
1(
1+
b1111111001111110 )
b1111111001111110 7
b1100 '
b1100 6
0%
#1055000
1#
b1111111001111110 4
b1111111001111110 A
b1111111001111110 N
1"
1%
#1060000
0%
#1065000
b1111111101001000 [
b11111111111101001000011011001000 \
0#
0"
1%
#1070000
b11111011100 q
b10000 p
0+
0*
0(
0%
#1075000
b1111111101001000 Y
b11111111111101001000011011001000 Z
1%
#1080000
1*
1(
1+
b11111011100 )
b11111011100 7
b10000 '
b10000 6
0%
#1085000
b1111111101000010 [
b1111111101000010 Y
b1111111101000010 W
b110000111 U
1#
b11111111111101000010011001001000 \
b11111111111101000010011001001000 Z
b11111111111101000010011001001000 X
b110000111111111001000 V
b11111011100 /
b11111011100 =
b11111011100 ]
b11111011100 .
b11111011100 ?
b11111011100 B
1"
1%
#1090000
0%
#1095000
b1111111101000010 U
b11111111111101000010011001001000 V
0#
0"
1%
#1100000
b100111010000 q
b1100 p
b10001 -
0+
0*
0(
0%
#1105000
1%
#1110000
1*
1(
1+
b100111010000 )
b100111010000 7
b1100 '
b1100 6
0%
#1115000
1#
b100111010000 4
b100111010000 A
b100111010000 N
1"
1%
#1120000
0%
#1125000
b10011010001 [
b10011010001111011000000 \
0#
0"
1%
#1130000
b11000101010 q
b10000 p
0+
0*
0(
0%
#1135000
b10011010001 Y
b10011010001111011000000 Z
1%
