LMS.v
module LMS (
    input Clk,
    input Rst,
    input mode_train,                 // 1 = training, 0 = filter mode
    input signed [15:0] x_in,        // Input sample Q4.12
    input signed [15:0] d_in,        // Desired output (used in training)
    output signed [15:0] y_out,      // LMS output
    output signed [15:0] err,        // Error (d_in - y_out)
    output signed [15:0] w0, w1, w2, w3 // Weights
);

    parameter signed [15:0] gamma = 16'b0000100000000000; // 0.5 in Q4.12

    // -----------------------------
    // Internal registers
    // -----------------------------
    reg signed [15:0] wn[0:3]; // Weights
    reg signed [15:0] x[0:3];  // Delay line
    reg signed [15:0] err_reg;

    // -----------------------------
    // Delay line
    // -----------------------------
    always @(posedge Clk or posedge Rst) begin
        if (Rst) begin
            x[0]<=16'sd0; x[1]<=16'sd0; x[2]<=16'sd0; x[3]<=16'sd0;
        end else begin
            x[3]<=x[2];
            x[2]<=x[1];
            x[1]<=x[0];
            x[0]<=x_in;
        end
    end

    // -----------------------------
    // Compute output
    // -----------------------------
    wire signed [31:0] y_acc = $signed(wn[0])*x[0] +
                               $signed(wn[1])*x[1] +
                               $signed(wn[2])*x[2] +
                               $signed(wn[3])*x[3];

    assign y_out = y_acc[27:12];

    // -----------------------------
    // Compute error (used only in training)
    // -----------------------------
    always @(posedge Clk or posedge Rst) begin
        if (Rst)
            err_reg <= 16'sd0;
        else if (mode_train)
            err_reg <= d_in - y_out;
        else
            err_reg <= 16'sd0;
    end
    assign err = err_reg;

    // -----------------------------
    // LMS weight update
    // -----------------------------
    wire signed [31:0] p0 = $signed(err_reg) * x[0];
    wire signed [31:0] p1 = $signed(err_reg) * x[1];
    wire signed [31:0] p2 = $signed(err_reg) * x[2];
    wire signed [31:0] p3 = $signed(err_reg) * x[3];

    wire signed [15:0] p0_q = p0[27:12];
    wire signed [15:0] p1_q = p1[27:12];
    wire signed [15:0] p2_q = p2[27:12];
    wire signed [15:0] p3_q = p3[27:12];

    wire signed [31:0] m0_long = $signed(gamma) * $signed(p0_q);
    wire signed [31:0] m1_long = $signed(gamma) * $signed(p1_q);
    wire signed [31:0] m2_long = $signed(gamma) * $signed(p2_q);
    wire signed [31:0] m3_long = $signed(gamma) * $signed(p3_q);

    wire signed [15:0] m0 = m0_long[27:12];
    wire signed [15:0] m1 = m1_long[27:12];
    wire signed [15:0] m2 = m2_long[27:12];
    wire signed [15:0] m3 = m3_long[27:12];

    wire signed [15:0] wn_u0 = wn[0] + m0;
    wire signed [15:0] wn_u1 = wn[1] + m1;
    wire signed [15:0] wn_u2 = wn[2] + m2;
    wire signed [15:0] wn_u3 = wn[3] + m3;

    always @(posedge Clk or posedge Rst) begin
        if (Rst)
            {wn[0],wn[1],wn[2],wn[3]} <= 64'sd0;
        else if (mode_train)
            {wn[0],wn[1],wn[2],wn[3]} <= {wn_u0,wn_u1,wn_u2,wn_u3};
    end

    assign w0=wn[0];
    assign w1=wn[1];
    assign w2=wn[2];
    assign w3=wn[3];

endmodule

wb_lms_tb.v
`timescale 1ns/1ps
module LMS_TB;

    reg Clk, Rst;
    reg mode_train;
    reg signed [15:0] x_in;
    reg signed [15:0] d_in;
    wire signed [15:0] y_out, err, w0, w1, w2, w3;

    integer i;
    reg signed [15:0] x_data[0:99];
    reg signed [15:0] d_data[0:99];

    integer csv_file;

    // Scaling factor for Q4.12
    real SF = 1.0/4096.0;

    // Instantiate LMS
    LMS dut (
        .Clk(Clk),
        .Rst(Rst),
        .mode_train(mode_train),
        .x_in(x_in),
        .d_in(d_in),
        .y_out(y_out),
        .err(err),
        .w0(w0), .w1(w1), .w2(w2), .w3(w3)
    );

    // Clock
    initial Clk = 0;
    always #5 Clk = ~Clk;  // 10ns period

    initial begin
        $dumpfile("LMS_tb.vcd");
        $dumpvars(0, LMS_TB);

        // Open CSV file
        csv_file = $fopen("lms_output.csv","w");
        $fwrite(csv_file,"time,x_in,y_out,d_in,err,w0,w1,w2,w3\n");

        // Reset
        Rst = 1; mode_train = 0; x_in = 0; d_in = 0;
        #20;
        Rst = 0;

        // Load input and desired data
        $readmemb("x_input.txt", x_data);
        $readmemb("d_input.txt", d_data);

        // -----------------------------
        // Training mode
        // -----------------------------
        mode_train = 1;
        for (i=0;i<100;i=i+1) begin
            x_in = x_data[i];
            d_in = d_data[i];
            #10; // wait 1 clock
            $fwrite(csv_file,"%0t,%d,%d,%d,%d,%d,%d,%d,%d\n",
                    $time, x_in, y_out, d_in, err, w0, w1, w2, w3);
        end

        // -----------------------------
        // Filter mode
        // -----------------------------
        mode_train = 0;
        for (i=0;i<100;i=i+1) begin
            x_in = x_data[i];
            d_in = 0; // not used
            #10;
            $fwrite(csv_file,"%0t,%d,%d,%d,%d,%d,%d,%d,%d\n",
                    $time, x_in, y_out, 0, 0, w0, w1, w2, w3);
        end

        $fclose(csv_file);
        $finish;
    end
endmodule

LMS_Periph/LMS_tb.vcd
$date
	Sat Oct 25 12:47:25 2025
$end
$version
	Icarus Verilog
$end
$timescale
	1ps
$end
$scope module LMS_TB $end
$var wire 16 ! y_out [15:0] $end
$var wire 16 " w3 [15:0] $end
$var wire 16 # w2 [15:0] $end
$var wire 16 $ w1 [15:0] $end
$var wire 16 % w0 [15:0] $end
$var wire 16 & err [15:0] $end
$var reg 1 ' Clk $end
$var reg 1 ( Rst $end
$var reg 16 ) d_in [15:0] $end
$var reg 1 * mode_train $end
$var reg 16 + x_in [15:0] $end
$var real 1 , SF $end
$var integer 32 - csv_file [31:0] $end
$var integer 32 . i [31:0] $end
$scope module dut $end
$var wire 1 ' Clk $end
$var wire 1 ( Rst $end
$var wire 16 / d_in [15:0] $end
$var wire 16 0 err [15:0] $end
$var wire 1 * mode_train $end
$var wire 16 1 w0 [15:0] $end
$var wire 16 2 w1 [15:0] $end
$var wire 16 3 w2 [15:0] $end
$var wire 16 4 w3 [15:0] $end
$var wire 16 5 x_in [15:0] $end
$var wire 16 6 y_out [15:0] $end
$var wire 32 7 y_acc [31:0] $end
$var wire 16 8 wn_u3 [15:0] $end
$var wire 16 9 wn_u2 [15:0] $end
$var wire 16 : wn_u1 [15:0] $end
$var wire 16 ; wn_u0 [15:0] $end
$var wire 16 < p3_q [15:0] $end
$var wire 32 = p3 [31:0] $end
$var wire 16 > p2_q [15:0] $end
$var wire 32 ? p2 [31:0] $end
$var wire 16 @ p1_q [15:0] $end
$var wire 32 A p1 [31:0] $end
$var wire 16 B p0_q [15:0] $end
$var wire 32 C p0 [31:0] $end
$var wire 32 D m3_long [31:0] $end
$var wire 16 E m3 [15:0] $end
$var wire 32 F m2_long [31:0] $end
$var wire 16 G m2 [15:0] $end
$var wire 32 H m1_long [31:0] $end
$var wire 16 I m1 [15:0] $end
$var wire 32 J m0_long [31:0] $end
$var wire 16 K m0 [15:0] $end
$var parameter 16 L gamma $end
$var reg 16 M err_reg [15:0] $end
$upscope $end
$upscope $end
$enddefinitions $end
$comment Show the parameter values. $end
$dumpall
b100000000000 L
$end
#0
$dumpvars
b0 M
b0 K
b0 J
b0 I
b0 H
b0 G
b0 F
b0 E
b0 D
b0 C
b0 B
b0 A
b0 @
b0 ?
b0 >
b0 =
b0 <
b0 ;
b0 :
b0 9
b0 8
b0 7
b0 6
b0 5
b0 4
b0 3
b0 2
b0 1
b0 0
b0 /
bx .
b10000000000000000000000000000011 -
r0.000244140625 ,
b0 +
0*
b0 )
1(
0'
b0 &
b0 %
b0 $
b0 #
b0 "
b0 !
$end
#5000
1'
#10000
0'
#15000
1'
#20000
0'
b0 .
1*
0(
#25000
1'
#30000
0'
b10011110010 +
b10011110010 5
b1 .
#35000
1'
#40000
0'
b10011110010 )
b10011110010 /
b100101101000 +
b100101101000 5
b10 .
#45000
b101110100 ;
b101110100 K
b11000011 :
b11000011 I
b101110100000000000000 J
b1011101000 B
b11000011100000000000 H
b110000111 @
b1011101000010001010000 C
b110000111010011000100 A
b10011110010 &
b10011110010 0
b10011110010 M
1'
#50000
0'
b100101101000 )
b100101101000 /
b110011110010 +
b110011110010 5
b11 .
#55000
b101110100 9
b101110100 G
b1111001110 K
b1011000011 I
b101110100000000000000 F
b1011101000 >
b1111001110000000000000 J
b11110011100 B
b1011000011100000000000 H
b10110000111 @
b110011111 !
b110011111 6
b1011101000010001010000 ?
b11110011100010001010000 C
b10110000111101001000000 A
b100101101000 &
b100101101000 0
b100101101000 M
b101110100 %
b101110100 1
b10101000010 ;
b11000011 $
b11000011 2
b110011111100111100000 7
b1110000110 :
1'
#60000
0'
b110011110010 )
b110011110010 /
b111100111000 +
b111100111000 5
b100 .
#65000
b10101100010 K
b10010010100 I
b1101010100 G
b111000000 8
b111000000 E
b10101100010100000000000 J
b101011000101 B
b100010110100 !
b100010110100 6
b10010010100100000000000 H
b100100101001 @
b1101010100000000000000 F
b11010101000 >
b111000000000000000000 D
b1110000000 <
b10101000010 %
b10101000010 1
b101010100100 ;
b1110000110 $
b1110000110 2
b100000011010 :
b101110100 #
b101110100 3
b10011001000 9
b101101010011 &
b101101010011 0
b101101010011 M
b101011000101011100101000 C
b100010110100110000111100 7
b100100101001100001110110 A
b11010101000010010111000 ?
b1110000000000001110110 =
1'
#70000
0'
b111100111000 )
b111100111000 /
b1000000000000 +
b1000000000000 5
b101 .
#75000
b1101000010 K
b1100011001 I
b1010100010 G
b111101010 E
b1101000010000000000000 J
b11010000100 B
b1100011001000000000000 H
b11000110010 @
b1010100010100000000000 F
b10101000101 >
b111101010000000000000 D
b1111010100 <
b1011100111110 !
b1011100111110 6
b11010000100000000000000 C
b11000110010100011100000 A
b10101000101100011001000 ?
b1111010100100110100000 =
b11010000100 &
b11010000100 0
b11010000100 M
b101010100100 %
b101010100100 1
b110111100110 ;
b100000011010 $
b100000011010 2
b101100110011 :
b10011001000 #
b10011001000 3
b11101101010 9
b111000000 "
b111000000 4
b1011100111110011011000000 7
b1110101010 8
1'
#80000
0'
b1000000000000 )
b1000000000000 /
b111100111000 +
b111100111000 5
b110 .
#85000
b1111110010001110 K
b1111110001100001 I
b1111110010001110 G
b1111110100010001 E
b11111111110010001110000000000000 J
b1111100100011100 B
b11111111110001100001000000000000 H
b1111100011000010 @
b11111111110010001110000000000000 F
b1111100100011100 >
b10001001101111 !
b10001001101111 6
b11111111110100010001100000000000 D
b1111101000100011 <
b110111100110 %
b110111100110 1
b101001110100 ;
b101100110011 $
b101100110011 2
b11110010100 :
b11101101010 #
b11101101010 3
b1111111000 9
b1110101010 "
b1110101010 4
b10111011 8
b1111100011000010 &
b1111100011000010 0
b1111100011000010 M
b11111111100100011100100001110000 C
b11111111100011000010000000000000 A
b11111111100100011100100001110000 ?
b10001001101111100000110100 7
b11111111101000100011111101100100 =
1'
#90000
0'
b111100111000 )
b111100111000 /
b110011110010 +
b110011110010 5
b111 .
#95000
b1111100000111010 K
b1111011011011100 I
b1111011001100100 G
b1111011011011100 E
b11111111100000111010000000000000 J
b1111000001110100 B
b11111111011011011100100000000000 H
b1110110110111001 @
b11111111011001100100100000000000 F
b1110110011001001 >
b11111111011011011100100000000000 D
b1110110110111001 <
b1010001010100 !
b1010001010100 6
b11111111000001110100001000000010 C
b11111110110110111001001011111000 A
b11111110110011001001000000000000 ?
b11111110110110111001001011111000 =
b1110110011001001 &
b1110110011001001 0
b1110110011001001 M
b101001110100 %
b101001110100 1
b1010101110 ;
b11110010100 $
b11110010100 2
b1111111001110000 :
b1111111000 #
b1111111000 3
b1111101001011100 9
b10111011 "
b10111011 4
b1010001010100001111110000 7
b1111011110010111 8
1'
#100000
0'
b110011110010 )
b110011110010 /
b100101101000 +
b100101101000 5
b1000 .
#105000
b1111110111010100 K
b1111110100000011 I
b1111110001111101 G
b1111110001001111 E
b11111111110111010100000000000000 J
b1111101110101000 B
b11111111110100000011000000000000 H
b1111101000000110 @
b11111111110001111101000000000000 F
b1111100011111010 >
b1111001010001001 !
b1111001010001001 6
b11111111110001001111000000000000 D
b1111100010011110 <
b1010101110 %
b1010101110 1
b10000010 ;
b1111111001110000 $
b1111111001110000 2
b1111101101110011 :
b1111101001011100 #
b1111101001011100 3
b1111011011011001 9
b1111011110010111 "
b1111011110010111 4
b1111001111100110 8
b1111100010011110 &
b1111100010011110 0
b1111100010011110 M
b11111111101110101000111000110000 C
b11111111101000000110110101011100 A
b11111111100011111010010010010000 ?
b11111111001010001001001010110000 7
b11111111100010011110000000000000 =
1'
#110000
0'
b100101101000 )
b100101101000 /
b10011110010 +
b10011110010 5
b1001 .
#115000
b1110001000 K
b11010111001 I
b100101000000 G
b101011100000 E
b1110001000100000000000 J
b11100010001 B
b11010111001000000000000 H
b110101110010 @
b100101000000100000000000 F
b1001010000001 >
b101011100000100000000000 D
b1010111000001 <
b1110101010010000 !
b1110101010010000 6
b11100010001101011001110 C
b110101110010000110011000 A
b1001010000001001011001110 ?
b1010111000001000111001000 =
b1011011011111 &
b1011011011111 0
b1011011011111 M
b10000010 %
b10000010 1
b10000001010 ;
b1111101101110011 $
b1111101101110011 2
b1000101100 :
b1111011011011001 #
b1111011011011001 3
b11001 9
b1111001111100110 "
b1111001111100110 4
b11111110101010010000111000001110 7
b1111111011000110 8
1'
#120000
0'
b10011110010 )
b10011110010 /
b0 +
b0 5
b1010 .
#125000
b0 K
b10000010011 I
b11111000001 G
b101010101100 E
b0 J
b0 B
b10000010011100000000000 H
b100000100111 @
b11111000001000000000000 F
b111110000010 >
b1111111110111100 !
b1111111110111100 6
b101010101100000000000000 D
b1010101011000 <
b10000001010 %
b10000001010 1
b10000001010 ;
b1000101100 $
b1000101100 2
b11000111111 :
b11001 #
b11001 3
b11111011010 9
b1111111011000110 "
b1111111011000110 4
b100101110010 8
b1101001100010 &
b1101001100010 0
b1101001100010 M
b0 C
b100000100111100010100100 A
b111110000010100111010000 ?
b11111111111110111100011111101100 7
b1010101011000100010100100 =
1'
#130000
0'
b0 )
b0 /
b1111101100001110 +
b1111101100001110 5
b1011 .
#135000
b1111111111 ;
b1111111111110101 K
b0 I
b1010 G
b10011 E
b11111111111111110101000000000000 J
b1111111111101010 B
b0 H
b0 @
b1010100000000000 F
b10101 >
b10011100000000000 D
b100111 <
b11010111011 !
b11010111011 6
b11111111111111101010111110111000 C
b0 A
b10101000001001000 ?
b100111111110100000 =
b1000100 &
b1000100 0
b1000100 M
b11000111111 $
b11000111111 2
b11000111111 :
b11111011010 #
b11111011010 3
b11111100100 9
b100101110010 "
b100101110010 4
b11010111011001011110000 7
b100110000101 8
1'
#140000
0'
b1111101100001110 )
b1111101100001110 /
b1111011010011000 +
b1111011010011000 5
b1100 .
#145000
b1101101110 K
b100000001100 :
b111001101 I
b0 G
b1111111000110010 E
b1101101110100000000000 J
b11011011101 B
b111001101100000000000 H
b1110011011 @
b0 F
b0 >
b1111111010101001 !
b1111111010101001 6
b11111111111000110010000000000000 D
b1111110001100100 <
b1111111111 %
b1111111111 1
b11101101101 ;
b11111100100 #
b11111100100 3
b11111100100 9
b100110000101 "
b100110000101 4
b11110110111 8
b1111010001010011 &
b1111010001010011 0
b1111010001010011 M
b11011011101001101001000 C
b1110011011110110001010 A
b0 ?
b11111111111010101001100110010100 7
b11111111110001100100001001110110 =
1'
#150000
0'
b1111011010011000 )
b1111011010011000 /
b1111001100001110 +
b1111001100001110 5
b1101 .
#155000
b100100100011 9
b100111111 G
b1101000011 K
b1001011110 I
b0 E
b100111111000000000000 F
b1001111110 >
b1101000011000000000000 J
b11010000110 B
b1001011110100000000000 H
b10010111101 @
b0 D
b0 <
b1111001011010010 !
b1111001011010010 6
b1001111110010000010010 ?
b11010000110110000010010 C
b10010111101111111101000 A
b0 =
b1111011111101111 &
b1111011111101111 0
b1111011111101111 M
b11101101101 %
b11101101101 1
b101010110000 ;
b100000001100 $
b100000001100 2
b101001101010 :
b11110110111 "
b11110110111 4
b11111111001011010010100010001110 7
b11110110111 8
1'
#160000
0'
b1111001100001110 )
b1111001100001110 /
b1111000011001000 +
b1111000011001000 5
b1110 .
#165000
b1111111111100011 K
b1111111111100111 I
b1111111111101110 G
b11110101101 8
b1111111111110110 E
b11111111111111100011000000000000 J
b1111111111000110 B
b11111111111111100111100000000000 H
b1111111111001111 @
b11111111111111101110000000000000 F
b1111111111011100 >
b1110010110100111 !
b1110010110100111 6
b11111111111111110110100000000000 D
b1111111111101101 <
b101010110000 %
b101010110000 1
b101010010011 ;
b101001101010 $
b101001101010 2
b101001010001 :
b100100100011 #
b100100100011 3
b100100010001 9
b111100 &
b111100 0
b111100 M
b11111111111111000110111011100000 C
b11111111111111001111011101001000 A
b11111111111111011100101110100000 ?
b11111110010110100111000100010110 7
b11111111111111101101011101001000 =
1'
#170000
0'
b1111000011001000 )
b1111000011001000 /
b1111000000000000 +
b1111000000000000 5
b1111 .
#175000
b1111101001101111 K
b1111101010110101 I
b1111101101111111 G
b1111110010111010 E
b11111111101001101111100000000000 J
b1111010011011111 B
b11111111101010110101000000000000 H
b1111010101101010 @
b11111111101101111111000000000000 F
b1111011011111110 >
b11111111110010111010100000000000 D
b1111100101110101 <
b1101111111000011 !
b1101111111000011 6
b11111111010011011111000000000000 C
b11111111010101101010000111001000 A
b11111111011011111110111011001110 ?
b11111111100101110101000110011000 =
b101100100001 &
b101100100001 0
b101100100001 M
b101010010011 %
b101010010011 1
b10100000010 ;
b101001010001 $
b101001010001 2
b10100000110 :
b100100010001 #
b100100010001 3
b10010010000 9
b11110101101 "
b11110101101 4
b11111101111111000011110111101110 7
b10001100111 8
1'
#180000
0'
b1111000000000000 )
b1111000000000000 /
b1111000011001000 +
b1111000011001000 5
b10000 .
#185000
b1111100001000110 K
b1111011111100001 I
b1111100001000110 G
b1111100101101110 E
b11111111100001000110100000000000 J
b1111000010001101 B
b11111111011111100001100000000000 H
b1110111111000011 @
b11111111100001000110100000000000 F
b1111000010001101 >
b1110111001001111 !
b1110111001001111 6
b11111111100101101110000000000000 D
b1111001011011100 <
b10100000010 %
b10100000010 1
b1111110101001000 ;
b10100000110 $
b10100000110 2
b1111110011100111 :
b10010010000 #
b10010010000 3
b1111110011010110 9
b10001100111 "
b10001100111 4
b1111110111010101 8
b1000000111101 &
b1000000111101 0
b1000000111101 M
b11111111000010001101111110101000 C
b11111110111111000011000000000000 A
b11111111000010001101111110101000 ?
b11111110111001001111110010110010 7
b11111111001011011100101001010110 =
1'
#190000
0'
b1111000011001000 )
b1111000011001000 /
b1111001100001110 +
b1111001100001110 5
b10001 .
#195000
b1111111011111111 K
b1111111011010010 I
b1111111011000011 G
b1111111011010010 E
b11111111111011111111100000000000 J
b1111110111111111 B
b11111111111011010010100000000000 H
b1111110110100101 @
b11111111111011000011100000000000 F
b1111110110000111 >
b11111111111011010010100000000000 D
b1111110110100101 <
b101001011111 !
b101001011111 6
b11111111110111111111110110011110 C
b11111111110110100101111010001000 A
b11111111110110000111000000000000 ?
b11111111110110100101111010001000 =
b1001111001 &
b1001111001 0
b1001111001 M
b1111110101001000 %
b1111110101001000 1
b1111110001000111 ;
b1111110011100111 $
b1111110011100111 2
b1111101110111001 :
b1111110011010110 #
b1111110011010110 3
b1111101110011001 9
b1111110111010101 "
b1111110111010101 4
b101001011111010011010000 7
b1111110010100111 8
1'
#200000
0'
b1111001100001110 )
b1111001100001110 /
b1111011010011000 +
b1111011010011000 5
b10010 .
#205000
b11011011010 K
b100101101110 I
b101100010110 G
b101110101000 E
b11011011010100000000000 J
b110110110101 B
b100101101110100000000000 H
b1001011011101 @
b101100010110100000000000 F
b1011000101101 >
b110100101111 !
b110100101111 6
b101110101000100000000000 D
b1011101010001 <
b1111110001000111 %
b1111110001000111 1
b1100100001 ;
b1111101110111001 $
b1111101110111001 2
b10100100111 :
b1111101110011001 #
b1111101110011001 3
b11010101111 9
b1111110010100111 "
b1111110010100111 4
b100001001111 8
b1110100010101111 &
b1110100010101111 0
b1110100010101111 M
b110110110101000111101000 C
b1001011011101011010010010 A
b1011000101101100010111000 ?
b110100101111001011001110 7
b1011101010001000000000000 =
1'
#210000
0'
b1111011010011000 )
b1111011010011000 /
b1111101100001110 +
b1111101100001110 5
b10011 .
#215000
b1101111101 K
b11010100011 I
b100100100011 G
b101010111110 E
b1101111101100000000000 J
b11011111011 B
b11010100011100000000000 H
b110101000111 @
b100100100011000000000000 F
b1001001000110 >
b101010111110000000000000 D
b1010101111100 <
b1110111010110001 !
b1110111010110001 6
b11011111011011010111110 C
b110101000111110001011000 A
b1001001000110111010111110 ?
b1010101111100101000001000 =
b1110100101101001 &
b1110100101101001 0
b1110100101101001 M
b1100100001 %
b1100100001 1
b11010011110 ;
b10100100111 $
b10100100111 2
b101111001010 :
b11010101111 #
b11010101111 3
b111111010010 9
b100001001111 "
b100001001111 4
b11111110111010110001100001000000 7
b1001100001101 8
1'
#220000
0'
b1111101100001110 )
b1111101100001110 /
b0 +
b0 5
b10100 .
#225000
b0 K
b1111111000010110 I
b1111110001011101 G
b1111101011111111 E
b0 J
b0 B
b11111111111000010110100000000000 H
b1111110000101101 @
b11111111110001011101100000000000 F
b1111100010111011 >
b1110001110100100 !
b1110001110100100 6
b11111111101011111111100000000000 D
b1111010111111111 <
b11010011110 %
b11010011110 1
b11010011110 ;
b101111001010 $
b101111001010 2
b100111100000 :
b111111010010 #
b111111010010 3
b110000101111 9
b1001100001101 "
b1001100001101 4
b111000001100 8
b110001011101 &
b110001011101 0
b110001011101 M
b0 C
b11111111110000101101110000010110 A
b11111111100010111011010100111000 ?
b11111110001110100100010101110010 7
b11111111010111111111010000010110 =
1'
#230000
0'
b0 )
b0 /
b10011110010 +
b10011110010 5
b10101 .
#235000
b101011111111 ;
b10001100001 K
b0 I
b1111101110011110 G
b1111011110101001 E
b10001100001100000000000 J
b100011000011 B
b0 H
b0 @
b11111111101110011110000000000000 F
b1111011100111100 >
b11111111011110101001100000000000 D
b1110111101010011 <
b1111011000000101 !
b1111011000000101 6
b100011000011111011111000 C
b0 A
b11111111011100111100000100001000 ?
b11111110111101010011111010100000 =
b1110001011100 &
b1110001011100 0
b1110001011100 M
b100111100000 $
b100111100000 2
b100111100000 :
b110000101111 #
b110000101111 3
b11111001101 9
b111000001100 "
b111000001100 4
b11111111011000000101100000001110 7
b10110110101 8
1'
#240000
0'
b10011110010 )
b10011110010 /
b100101101000 +
b100101101000 5
b10110 .
#245000
b10001100011 K
b110000101110 :
b1001001110 I
b0 G
b1111110110110001 E
b10001100011000000000000 J
b100011000110 B
b1001001110100000000000 H
b10010011101 @
b0 F
b0 >
b11111000000 !
b11111000000 6
b11111111110110110001000000000000 D
b1111101101100010 <
b101011111111 %
b101011111111 1
b111101100010 ;
b11111001101 #
b11111001101 3
b11111001101 9
b10110110101 "
b10110110101 4
b1101100110 8
b111011101101 &
b111011101101 0
b111011101101 M
b100011000110010101001000 C
b10010011101000000001010 A
b0 ?
b11111000000101100111110 7
b11111111101101100010111111110110 =
1'
#250000
0'
b100101101000 )
b100101101000 /
b110011110010 +
b110011110010 5
b10111 .
#255000
b100000001110 9
b1000001 G
b10101011 K
b1111100 I
b0 E
b1000001100000000000 F
b10000011 >
b10101011100000000000 J
b101010111 B
b1111100100000000000 H
b11111001 @
b0 D
b0 <
b1011000000100 !
b1011000000100 6
b10000011000011010000 ?
b101010111000011010000 C
b11111001010001000000 A
b0 =
b110101000 &
b110101000 0
b110101000 M
b111101100010 %
b111101100010 1
b1000000001101 ;
b110000101110 $
b110000101110 2
b110010101010 :
b1101100110 "
b1101100110 4
b1011000000100011100011110 7
b1101100110 8
1'
#260000
0'
b110011110010 )
b110011110010 /
b111100111000 +
b111100111000 5
b11000 .
#265000
b1111101110101111 K
b1111110001010100 I
b1111110101010101 G
b111111111 8
b1111111010011001 E
b11111111101110101111100000000000 J
b1111011101011111 B
b11111111110001010100100000000000 H
b1111100010101001 @
b11111111110101010101000000000000 F
b1111101010101010 >
b1111101001100 !
b1111101001100 6
b11111111111010011001000000000000 D
b1111110100110010 <
b1000000001101 %
b1000000001101 1
b101110111100 ;
b110010101010 $
b110010101010 2
b100011111110 :
b100000001110 #
b100000001110 3
b10101100011 9
b1111011011101110 &
b1111011011101110 0
b1111011011101110 M
b11111111011101011111011000010000 C
b11111111100010101001010011111100 A
b11111111101010101010111010110000 ?
b1111101001100100010101000 7
b11111111110100110010010011111100 =
1'
#270000
0'
b111100111000 )
b111100111000 /
b1000000000000 +
b1000000000000 5
b11001 .
#275000
b1111011111110110 K
b1111100001011010 I
b1111100101111110 G
b1111101101000110 E
b11111111011111110110000000000000 J
b1110111111101100 B
b11111111100001011010000000000000 H
b1111000010110100 @
b11111111100101111110100000000000 F
b1111001011111101 >
b11111111101101000110000000000000 D
b1111011010001100 <
b1100111010001 !
b1100111010001 6
b11111110111111101100000000000000 C
b11111111000010110100111110100000 A
b11111111001011111101110100011000 ?
b11111111011010001100001111100000 =
b1110111111101100 &
b1110111111101100 0
b1110111111101100 M
b101110111100 %
b101110111100 1
b1110110010 ;
b100011111110 $
b100011111110 2
b101011000 :
b10101100011 #
b10101100011 3
b1111111011100001 9
b111111111 "
b111111111 4
b1100111010001101110111110 7
b1111110101000101 8
1'
#280000
0'
b1000000000000 )
b1000000000000 /
b111100111000 +
b111100111000 5
b11010 .
#285000
b1111101101010100 K
b1111101100010111 I
b1111101101010100 G
b1111110000000111 E
b11111111101101010100100000000000 J
b1111011010101001 B
b11111111101100010111100000000000 H
b1111011000101111 @
b11111111101101010100100000000000 F
b1111011010101001 >
b110010101 !
b110010101 6
b11111111110000000111000000000000 D
b1111100000001110 <
b1110110010 %
b1110110010 1
b1111111100000110 ;
b101011000 $
b101011000 2
b1111110001101111 :
b1111111011100001 #
b1111111011100001 3
b1111101000110101 9
b1111110101000101 "
b1111110101000101 4
b1111100101001100 8
b1111011000101111 &
b1111011000101111 0
b1111011000101111 M
b11111111011010101001101101001000 C
b11111111011000101111000000000000 A
b11111111011010101001101101001000 ?
b110010101010001100010 7
b11111111100000001110110001101110 =
1'
#290000
0'
b111100111000 )
b111100111000 /
b110011110010 +
b110011110010 5
b11011 .
#295000
b10110000100 K
b11001111100 I
b11011010001 G
b11001111100 E
b10110000100000000000000 J
b101100001000 B
b11001111100000000000000 H
b110011111000 @
b11011010001100000000000 F
b110110100011 >
b11001111100000000000000 D
b110011111000 <
b1110111110100110 !
b1110111110100110 6
b101100001000100000010110 C
b110011111000100010101000 A
b110110100011000000000000 ?
b110011111000100010101000 =
b110110100011 &
b110110100011 0
b110110100011 M
b1111111100000110 %
b1111111100000110 1
b10010001010 ;
b1111110001101111 $
b1111110001101111 2
b1011101011 :
b1111101000110101 #
b1111101000110101 3
b100000110 9
b1111100101001100 "
b1111100101001100 4
b11111110111110100110000110010100 7
b1111111111001000 8
1'
#300000
0'
b110011110010 )
b110011110010 /
b100101101000 +
b100101101000 5
b11100 .
#305000
b100010011100 K
b101111011010 I
b110111101110 G
b111010100110 E
b100010011100100000000000 J
b1000100111001 B
b101111011010000000000000 H
b1011110110100 @
b110111101110100000000000 F
b1101111011101 >
b10111001000 !
b10111001000 6
b111010100110000000000000 D
b1110101001100 <
b10010001010 %
b10010001010 1
b110100100110 ;
b1011101011 $
b1011101011 2
b111011000101 :
b100000110 #
b100000110 3
b111011110100 9
b1111111111001000 "
b1111111111001000 4
b111001101110 8
b1110101001100 &
b1110101001100 0
b1110101001100 M
b1000100111001001011100000 C
b1011110110100000111011000 A
b1101111011101110010100000 ?
b10111001000101110000110 7
b1110101001100000000000000 =
1'
#310000
0'
b100101101000 )
b100101101000 /
b10011110010 +
b10011110010 5
b11101 .
#315000
b10001111 K
b100010000 I
b101110111 G
b110111001 E
b10001111000000000000 J
b100011110 B
b100010000100000000000 H
b1000100001 @
b101110111000000000000 F
b1011101110 >
b110111001000000000000 D
b1101110010 <
b10011010010001 !
b10011010010001 6
b100011110110101000000 C
b1000100001100100000000 A
b1011101110110101000000 ?
b1101110010101100000000 =
b1110100000 &
b1110100000 0
b1110100000 M
b110100100110 %
b110100100110 1
b110110110101 ;
b111011000101 $
b111011000101 2
b111111010101 :
b111011110100 #
b111011110100 3
b1000001101011 9
b111001101110 "
b111001101110 4
b10011010010001111110101100 7
b1000000100111 8
1'
#320000
0'
b10011110010 )
b10011110010 /
b0 +
b0 5
b11110 .
#325000
b0 K
b1111101011001101 I
b1111011000011110 G
b1111001001100110 E
b0 J
b0 B
b11111111101011001101100000000000 H
b1111010110011011 @
b11111111011000011110000000000000 F
b1110110000111100 >
b1101110011101 !
b1101110011101 6
b11111111001001100110000000000000 D
b1110010011001100 <
b110110110101 %
b110110110101 1
b110110110101 ;
b111111010101 $
b111111010101 2
b101010100010 :
b1000001101011 #
b1000001101011 3
b11010001001 9
b1000000100111 "
b1000000100111 4
b1010001101 8
b1101111001100001 &
b1101111001100001 0
b1101111001100001 M
b0 C
b11111111010110011011101110110010 A
b11111110110000111100000001101000 ?
b1101110011101001010110000 7
b11111110010011001100001110110010 =
1'
#330000
0'
b0 )
b0 /
b1111101100001110 +
b1111101100001110 5
b11111 .
#335000
b1000111111001 ;
b10001000100 K
b0 I
b1111101110111011 G
b1111011111100010 E
b10001000100000000000000 J
b100010001000 B
b0 H
b0 @
b11111111101110111011100000000000 F
b1111011101110111 >
b11111111011111100010000000000000 D
b1110111111000100 <
b1111111101001000 !
b1111111101001000 6
b100010001000111001101010 C
b0 A
b11111111011101110111000110010110 ?
b11111110111111000100001100111000 =
b1110010001100011 &
b1110010001100011 0
b1110010001100011 M
b101010100010 $
b101010100010 2
b101010100010 :
b11010001001 #
b11010001001 3
b1001000100 9
b1010001101 "
b1010001101 4
b11111111111101001000011010110000 7
b1111101001101111 8
1'
#340000
0'
b1111101100001110 )
b1111101100001110 /
b1111011010011000 +
b1111011010011000 5
b100000 .
