LMS.v
module LMS (
    input Clk,
    input Rst,
    input mode_train,                 // 1 = training, 0 = filter mode
    input signed [15:0] x_in,        // Input sample Q4.12
    input signed [15:0] d_in,        // Desired output (used in training)
    output signed [15:0] y_out,      // LMS output
    output signed [15:0] err,        // Error (d_in - y_out)
    output signed [15:0] w0, w1, w2, w3 // Weights
);

    parameter signed [15:0] gamma = 16'b0000100000000000; // 0.5 in Q4.12

    // -----------------------------
    // Internal registers
    // -----------------------------
    reg signed [15:0] wn[0:3]; // Weights
    reg signed [15:0] x[0:3];  // Delay line
    reg signed [15:0] err_reg;

    // -----------------------------
    // Delay line
    // -----------------------------
    always @(posedge Clk or posedge Rst) begin
        if (Rst) begin
            x[0]<=16'sd0; x[1]<=16'sd0; x[2]<=16'sd0; x[3]<=16'sd0;
        end else begin
            x[3]<=x[2];
            x[2]<=x[1];
            x[1]<=x[0];
            x[0]<=x_in;
        end
    end

    // -----------------------------
    // Compute output
    // -----------------------------
    wire signed [31:0] y_acc = $signed(wn[0])*x[0] +
                               $signed(wn[1])*x[1] +
                               $signed(wn[2])*x[2] +
                               $signed(wn[3])*x[3];

    assign y_out = y_acc[27:12];

    // -----------------------------
    // Compute error (used only in training)
    // -----------------------------
    always @(posedge Clk or posedge Rst) begin
        if (Rst)
            err_reg <= 16'sd0;
        else if (mode_train)
            err_reg <= d_in - y_out;
        else
            err_reg <= 16'sd0;
    end
    assign err = err_reg;

    // -----------------------------
    // LMS weight update
    // -----------------------------
    wire signed [31:0] p0 = $signed(err_reg) * x[0];
    wire signed [31:0] p1 = $signed(err_reg) * x[1];
    wire signed [31:0] p2 = $signed(err_reg) * x[2];
    wire signed [31:0] p3 = $signed(err_reg) * x[3];

    wire signed [15:0] p0_q = p0[27:12];
    wire signed [15:0] p1_q = p1[27:12];
    wire signed [15:0] p2_q = p2[27:12];
    wire signed [15:0] p3_q = p3[27:12];

    wire signed [31:0] m0_long = $signed(gamma) * $signed(p0_q);
    wire signed [31:0] m1_long = $signed(gamma) * $signed(p1_q);
    wire signed [31:0] m2_long = $signed(gamma) * $signed(p2_q);
    wire signed [31:0] m3_long = $signed(gamma) * $signed(p3_q);

    wire signed [15:0] m0 = m0_long[27:12];
    wire signed [15:0] m1 = m1_long[27:12];
    wire signed [15:0] m2 = m2_long[27:12];
    wire signed [15:0] m3 = m3_long[27:12];

    wire signed [15:0] wn_u0 = wn[0] + m0;
    wire signed [15:0] wn_u1 = wn[1] + m1;
    wire signed [15:0] wn_u2 = wn[2] + m2;
    wire signed [15:0] wn_u3 = wn[3] + m3;

    always @(posedge Clk or posedge Rst) begin
        if (Rst)
            {wn[0],wn[1],wn[2],wn[3]} <= 64'sd0;
        else if (mode_train)
            {wn[0],wn[1],wn[2],wn[3]} <= {wn_u0,wn_u1,wn_u2,wn_u3};
    end

    assign w0=wn[0];
    assign w1=wn[1];
    assign w2=wn[2];
    assign w3=wn[3];

endmodule

wb_lms.v
module wb_lms (
    input  wire        Clk,
    input  wire        Rst,
    input  wire        wb_cyc_i,
    input  wire        wb_stb_i,
    input  wire        wb_we_i,
    input  wire [31:0] wb_adr_i,
    input  wire [15:0] wb_dat_i,
    output reg  [15:0] wb_dat_o,
    output reg         wb_ack_o,
    output reg         irq_o
);

    // -----------------------------
    // LMS interface signals
    // -----------------------------
    reg signed [15:0] x_in_reg, d_in_reg;
    reg mode_train_reg;
    wire signed [15:0] y_out, err, w0, w1, w2, w3;

    LMS dut (
        .Clk(Clk),
        .Rst(Rst),
        .mode_train(mode_train_reg),
        .x_in(x_in_reg),
        .d_in(d_in_reg),
        .y_out(y_out),
        .err(err),
        .w0(w0),
        .w1(w1),
        .w2(w2),
        .w3(w3)
    );

    // -----------------------------
    // Wishbone logic
    // -----------------------------
    always @(posedge Clk or posedge Rst) begin
        if (Rst) begin
            wb_ack_o       <= 0;
            wb_dat_o       <= 0;
            irq_o          <= 0;
            x_in_reg       <= 0;
            d_in_reg       <= 0;
            mode_train_reg <= 0;
        end else begin
            wb_ack_o <= 0;
            irq_o    <= 0;
            if (wb_cyc_i && wb_stb_i && !wb_ack_o) begin
                wb_ack_o <= 1;
                if (wb_we_i) begin
                    case (wb_adr_i[5:2])
                        4'h0: x_in_reg       <= wb_dat_i;
                        4'h1: d_in_reg       <= wb_dat_i;
                        4'h2: mode_train_reg <= wb_dat_i[0]; // only LSB
                    endcase
                    irq_o <= 1; // optional interrupt on write
                end else begin
                    case (wb_adr_i[5:2])
                        4'h3: wb_dat_o <= y_out;
                        4'h4: wb_dat_o <= err;
                        4'h5: wb_dat_o <= w0;
                        4'h6: wb_dat_o <= w1;
                        4'h7: wb_dat_o <= w2;
                        4'h8: wb_dat_o <= w3;
                        default: wb_dat_o <= 16'd0;
                    endcase
                end
            end
        end
    end

endmodule

LMS_Periph/wb_lms_tb.v
`timescale 1ns/1ps
module wb_lms_tb;

    reg Clk, Rst;
    reg wb_cyc_i, wb_stb_i, wb_we_i;
    reg [31:0] wb_adr_i;
    reg [15:0] wb_dat_i;
    wire [15:0] wb_dat_o;
    wire wb_ack_o, irq_o;

    integer i;
    reg signed [15:0] x_data[0:99];
    reg signed [15:0] d_data[0:99];
    integer csv_file;

    real SF = 1.0/4096.0; // Q4.12 scaling

    // Instantiate WB-LMS
    wb_lms dut (
        .Clk(Clk),
        .Rst(Rst),
        .wb_cyc_i(wb_cyc_i),
        .wb_stb_i(wb_stb_i),
        .wb_we_i(wb_we_i),
        .wb_adr_i(wb_adr_i),
        .wb_dat_i(wb_dat_i),
        .wb_dat_o(wb_dat_o),
        .wb_ack_o(wb_ack_o),
        .irq_o(irq_o)
    );

    // Clock generation
    initial Clk = 0;
    always #5 Clk = ~Clk;

    // -----------------------------
    // Tasks for WB access
    // -----------------------------
    task wb_write(input [31:0] addr, input [15:0] data);
    begin
        @(negedge Clk);
        wb_cyc_i <= 1; wb_stb_i <= 1; wb_we_i <= 1;
        wb_adr_i <= addr;
        wb_dat_i <= data;
        @(posedge wb_ack_o);
        @(negedge Clk);
        wb_cyc_i <= 0; wb_stb_i <= 0; wb_we_i <= 0;
    end
    endtask

    task wb_read(input [31:0] addr, output [15:0] data_out);
    begin
        @(negedge Clk);
        wb_cyc_i <= 1; wb_stb_i <= 1; wb_we_i <= 0;
        wb_adr_i <= addr;
        @(posedge wb_ack_o);
        data_out = wb_dat_o;
        @(negedge Clk);
        wb_cyc_i <= 0; wb_stb_i <= 0;
    end
    endtask

    // -----------------------------
    // Main test
    // -----------------------------
    initial begin
        $dumpfile("wb_lms_tb.vcd");
        $dumpvars(0, wb_lms_tb);

        // Open CSV
        csv_file = $fopen("wb_lms_output.csv","w");
        $fwrite(csv_file,"time,x_in,y_out,d_in,err,w0,w1,w2,w3\n");

        // Reset
        Clk <= 0;
        Rst <= 1; wb_cyc_i=0; wb_stb_i=0; wb_we_i=0;
        wb_adr_i=0; wb_dat_i=0;
        #20;
        Rst <= 0;

        // Load data
        $readmemb("x_input.txt", x_data);
        $readmemb("d_input.txt", d_data);

        // -----------------------------
        // Training Mode
        // -----------------------------
        wb_write(32'h08, 16'd1); // mode_train = 1

        for(i=0;i<100;i=i+1) begin
            wb_write(32'h00, x_data[i]); // x_in
            wb_write(32'h04, d_data[i]); // d_in

            // Read outputs for logging
            #(10);
            log_csv(i);
        end

        // -----------------------------
        // Filter Mode
        // -----------------------------
        wb_write(32'h08, 16'd0); // mode_train = 0

        for(i=0;i<100;i=i+1) begin
            wb_write(32'h00, x_data[i]); // x_in
            wb_write(32'h04, 16'd0);     // d_in unused

            #(10);
            log_csv(i);
        end

        $fclose(csv_file);
        $finish;
    end

    // -----------------------------
    // Logging task
    // -----------------------------
    task log_csv(input integer idx);
        reg signed [15:0] y, e, w_0, w_1, w_2, w_3;
    begin
        wb_read(32'h0C, y);
        wb_read(32'h10, e);
        wb_read(32'h14, w_0);
        wb_read(32'h18, w_1);
        wb_read(32'h1C, w_2);
        wb_read(32'h20, w_3);

        $fwrite(csv_file,"%0t,%d,%d,%d,%d,%d,%d,%d,%d\n",
                $time, x_data[idx], y, d_data[idx], e, w_0, w_1, w_2, w_3);
    end
    endtask

endmodule

LMS_Periph/wb_lms_tb.vcd
$date
	Sat Oct 25 19:30:35 2025
$end
$version
	Icarus Verilog
$end
$timescale
	1ps
$end
$scope module wb_lms_tb $end
$var wire 16 ! wb_dat_o [15:0] $end
$var wire 1 " wb_ack_o $end
$var wire 1 # irq_o $end
$var reg 1 $ Clk $end
$var reg 1 % Rst $end
$var reg 32 & wb_adr_i [31:0] $end
$var reg 1 ' wb_cyc_i $end
$var reg 16 ( wb_dat_i [15:0] $end
$var reg 1 ) wb_stb_i $end
$var reg 1 * wb_we_i $end
$var real 1 + SF $end
$var integer 32 , csv_file [31:0] $end
$var integer 32 - i [31:0] $end
$scope module dut $end
$var wire 1 $ Clk $end
$var wire 1 % Rst $end
$var wire 32 . wb_adr_i [31:0] $end
$var wire 1 ' wb_cyc_i $end
$var wire 16 / wb_dat_i [15:0] $end
$var wire 1 ) wb_stb_i $end
$var wire 1 * wb_we_i $end
$var wire 16 0 y_out [15:0] $end
$var wire 16 1 w3 [15:0] $end
$var wire 16 2 w2 [15:0] $end
$var wire 16 3 w1 [15:0] $end
$var wire 16 4 w0 [15:0] $end
$var wire 16 5 err [15:0] $end
$var reg 16 6 d_in_reg [15:0] $end
$var reg 1 # irq_o $end
$var reg 1 7 mode_train_reg $end
$var reg 1 " wb_ack_o $end
$var reg 16 8 wb_dat_o [15:0] $end
$var reg 16 9 x_in_reg [15:0] $end
$scope module dut $end
$var wire 1 $ Clk $end
$var wire 1 % Rst $end
$var wire 16 : d_in [15:0] $end
$var wire 16 ; err [15:0] $end
$var wire 1 7 mode_train $end
$var wire 16 < w0 [15:0] $end
$var wire 16 = w1 [15:0] $end
$var wire 16 > w2 [15:0] $end
$var wire 16 ? w3 [15:0] $end
$var wire 16 @ x_in [15:0] $end
$var wire 16 A y_out [15:0] $end
$var wire 32 B y_acc [31:0] $end
$var wire 16 C wn_u3 [15:0] $end
$var wire 16 D wn_u2 [15:0] $end
$var wire 16 E wn_u1 [15:0] $end
$var wire 16 F wn_u0 [15:0] $end
$var wire 16 G p3_q [15:0] $end
$var wire 32 H p3 [31:0] $end
$var wire 16 I p2_q [15:0] $end
$var wire 32 J p2 [31:0] $end
$var wire 16 K p1_q [15:0] $end
$var wire 32 L p1 [31:0] $end
$var wire 16 M p0_q [15:0] $end
$var wire 32 N p0 [31:0] $end
$var wire 32 O m3_long [31:0] $end
$var wire 16 P m3 [15:0] $end
$var wire 32 Q m2_long [31:0] $end
$var wire 16 R m2 [15:0] $end
$var wire 32 S m1_long [31:0] $end
$var wire 16 T m1 [15:0] $end
$var wire 32 U m0_long [31:0] $end
$var wire 16 V m0 [15:0] $end
$var parameter 16 W gamma $end
$var reg 16 X err_reg [15:0] $end
$upscope $end
$upscope $end
$scope task log_csv $end
$var reg 16 Y e [15:0] $end
$var reg 16 Z w_0 [15:0] $end
$var reg 16 [ w_1 [15:0] $end
$var reg 16 \ w_2 [15:0] $end
$var reg 16 ] w_3 [15:0] $end
$var reg 16 ^ y [15:0] $end
$var integer 32 _ idx [31:0] $end
$upscope $end
$scope task wb_read $end
$var reg 32 ` addr [31:0] $end
$var reg 16 a data_out [15:0] $end
$upscope $end
$scope task wb_write $end
$var reg 32 b addr [31:0] $end
$var reg 16 c data [15:0] $end
$upscope $end
$upscope $end
$enddefinitions $end
$comment Show the parameter values. $end
$dumpall
b100000000000 W
$end
#0
$dumpvars
bx c
bx b
bx a
bx `
bx _
bx ^
bx ]
bx \
bx [
bx Z
bx Y
b0 X
b0 V
b0 U
b0 T
b0 S
b0 R
b0 Q
b0 P
b0 O
b0 N
b0 M
b0 L
b0 K
b0 J
b0 I
b0 H
b0 G
b0 F
b0 E
b0 D
b0 C
b0 B
b0 A
b0 @
b0 ?
b0 >
b0 =
b0 <
b0 ;
b0 :
b0 9
b0 8
07
b0 6
b0 5
b0 4
b0 3
b0 2
b0 1
b0 0
b0 /
b0 .
bx -
b10000000000000000000000000000011 ,
r0.000244140625 +
0*
0)
b0 (
0'
b0 &
1%
0$
0#
0"
b0 !
$end
#5000
1$
#10000
0$
#15000
1$
#20000
b1 (
b1 /
b1000 &
b1000 .
1*
1)
1'
0%
0$
b1 c
b1000 b
#25000
1#
17
1"
1$
#30000
0*
0)
0'
b0 c
b0 b
b0 -
0$
#35000
0#
0"
1$
#40000
b0 (
b0 /
b0 &
b0 .
1*
1)
1'
0$
#45000
1#
1"
1$
#50000
0*
0)
0'
b100 b
0$
#55000
0#
0"
1$
#60000
b100 &
b100 .
1*
1)
1'
0$
#65000
1#
1"
1$
#70000
0*
0)
0'
0$
#75000
0#
0"
1$
#80000
b1100 &
b1100 .
1)
1'
0$
b1100 `
b0 _
#85000
b0 a
1"
1$
#90000
0)
0'
b10000 `
b0 ^
0$
#95000
0"
1$
#100000
b10000 &
b10000 .
1)
1'
0$
#105000
1"
1$
#110000
0)
0'
b10100 `
b0 Y
0$
#115000
0"
1$
#120000
b10100 &
b10100 .
1)
1'
0$
#125000
1"
1$
#130000
0)
0'
b11000 `
b0 Z
0$
#135000
0"
1$
#140000
b11000 &
b11000 .
1)
1'
0$
#145000
1"
1$
#150000
0)
0'
b11100 `
b0 [
0$
#155000
0"
1$
#160000
b11100 &
b11100 .
1)
1'
0$
#165000
1"
1$
#170000
0)
0'
b100000 `
b0 \
0$
#175000
0"
1$
#180000
b100000 &
b100000 .
1)
1'
0$
#185000
1"
1$
#190000
0)
0'
b10011110010 c
b0 b
b1 -
b0 ]
0$
#195000
0"
1$
#200000
b10011110010 (
b10011110010 /
b0 &
b0 .
1*
1)
1'
0$
#205000
1#
b10011110010 9
b10011110010 @
1"
1$
#210000
0*
0)
0'
b0 c
b100 b
0$
#215000
0#
0"
1$
#220000
b0 (
b0 /
b100 &
b100 .
1*
1)
1'
0$
#225000
1#
1"
1$
#230000
0*
0)
0'
0$
#235000
0#
0"
1$
#240000
b1100 &
b1100 .
1)
1'
0$
b1100 `
b1 _
#245000
1"
1$
#250000
0)
0'
b10000 `
0$
#255000
0"
1$
#260000
b10000 &
b10000 .
1)
1'
0$
#265000
1"
1$
#270000
0)
0'
b10100 `
0$
#275000
0"
1$
#280000
b10100 &
b10100 .
1)
1'
0$
#285000
1"
1$
#290000
0)
0'
b11000 `
0$
#295000
0"
1$
#300000
b11000 &
b11000 .
1)
1'
0$
#305000
1"
1$
#310000
0)
0'
b11100 `
0$
#315000
0"
1$
#320000
b11100 &
b11100 .
1)
1'
0$
#325000
1"
1$
#330000
0)
0'
b100000 `
0$
#335000
0"
1$
#340000
b100000 &
b100000 .
1)
1'
0$
#345000
1"
1$
#350000
0)
0'
b100101101000 c
b0 b
b10 -
0$
#355000
0"
1$
#360000
b100101101000 (
b100101101000 /
b0 &
b0 .
1*
1)
1'
0$
#365000
1#
b100101101000 9
b100101101000 @
1"
1$
#370000
0*
0)
0'
b10011110010 c
b100 b
0$
#375000
0#
0"
1$
#380000
b10011110010 (
b10011110010 /
b100 &
b100 .
1*
1)
1'
0$
#385000
1#
b10011110010 6
b10011110010 :
1"
1$
#390000
0*
0)
0'
0$
#395000
b101110100 F
b101110100 V
b101110100 E
b101110100 T
b101110100 D
b101110100 R
b11000011 C
b11000011 P
b101110100000000000000 U
b1011101000 M
b101110100000000000000 S
b1011101000 K
b101110100000000000000 Q
b1011101000 I
b11000011100000000000 O
b110000111 G
b1011101000010001010000 N
b1011101000010001010000 L
b1011101000010001010000 J
b110000111010011000100 H
b10011110010 5
b10011110010 ;
b10011110010 X
0#
0"
1$
#400000
b1100 &
b1100 .
1)
1'
0$
b1100 `
b10 _
#405000
b101110100 P
b1100000010 0
b1100000010 A
b101110100000000000000 O
b1011101000 G
1"
b101110100 4
b101110100 <
b1011101000 F
b101110100 3
b101110100 =
b1011101000 E
b101110100 2
b101110100 >
b1011101000 D
b11000011 1
b11000011 ?
b1100000010101110011000 B
b1000110111 C
b1011101000010001010000 H
1$
#410000
0)
0'
b10000 `
0$
#415000
b10010001 V
b10010001 T
b10010001 R
b10010001 P
b10010001100000000000 U
b100100011 M
b10010001100000000000 S
b100100011 K
b10010001100000000000 Q
b100100011 I
b10010001100000000000 O
b100100011 G
b11001101101 0
b11001101101 A
b100100011100110000000 N
b100100011100110000000 L
b100100011100110000000 J
b100100011100110000000 H
b111110000 5
b111110000 ;
b111110000 X
b1011101000 4
b1011101000 <
b1101111001 F
b1011101000 3
b1011101000 =
b1101111001 E
b1011101000 2
b1011101000 >
b1101111001 D
b1000110111 1
b1000110111 ?
b11001101101100000011000 B
b1011001000 C
0"
1$
#420000
b10000 &
b10000 .
1)
1'
0$
#425000
b1111111110010000 V
b1111111110010000 T
b1111111110010000 R
b1111111110010000 P
b111110000 a
b11111000010 0
b11111000010 A
b11111111111110010000100000000000 U
b1111111100100001 M
b11111111111110010000100000000000 S
b1111111100100001 K
b11111111111110010000100000000000 Q
b1111111100100001 I
b11111111111110010000100000000000 O
b1111111100100001 G
b111110000 !
b111110000 8
1"
b1101111001 4
b1101111001 <
b1100001001 F
b1101111001 3
b1101111001 =
b1100001001 E
b1101111001 2
b1101111001 >
b1100001001 D
b1011001000 1
b1011001000 ?
b11111000010011110111000 B
b1001011000 C
b11111111111100100001001100001000 N
b11111111111100100001001100001000 L
b11111111111100100001001100001000 J
b11111111111100100001001100001000 H
b1111111010000101 5
b1111111010000101 ;
b1111111010000101 X
1$
#430000
0)
0'
b10100 `
b111110000 Y
0$
#435000
b1111111100101100 V
b1111111100101100 T
b1111111100101100 R
b1111111100101100 P
b11111111111100101100000000000000 U
b1111111001011000 M
b11111111111100101100000000000000 S
b1111111001011000 K
b11111111111100101100000000000000 Q
b1111111001011000 I
b11111111111100101100000000000000 O
b1111111001011000 G
b11010111011 0
b11010111011 A
b11111111111001011000101110000000 N
b11111111111001011000101110000000 L
b11111111111001011000101110000000 J
b11111111111001011000101110000000 H
b1111110100110000 5
b1111110100110000 ;
b1111110100110000 X
b1100001001 4
b1100001001 <
b1000110101 F
b1100001001 3
b1100001001 =
b1000110101 E
b1100001001 2
b1100001001 >
b1000110101 D
b1001011000 1
b1001011000 ?
b11010111011000110111000 B
b110000100 C
0"
1$
#440000
b10100 &
b10100 .
1)
1'
0$
#445000
b1111111101111001 V
b1111111101111001 T
b1111111101111001 R
b1111111101111001 P
b1100001001 a
b10011001000 0
b10011001000 A
b11111111111101111001100000000000 U
b1111111011110011 M
b11111111111101111001100000000000 S
b1111111011110011 K
b11111111111101111001100000000000 Q
b1111111011110011 I
b11111111111101111001100000000000 O
b1111111011110011 G
b1100001001 !
b1100001001 8
1"
b1000110101 4
b1000110101 <
b110101110 F
b1000110101 3
b1000110101 =
b110101110 E
b1000110101 2
b1000110101 >
b110101110 D
b110000100 1
b110000100 ?
b10011001000100100111000 B
b11111101 C
b11111111111011110011010101011000 N
b11111111111011110011010101011000 L
b11111111111011110011010101011000 J
b11111111111011110011010101011000 H
b1111111000110111 5
b1111111000110111 ;
b1111111000110111 X
1$
#450000
0)
0'
b11000 `
b1100001001 Z
0$
#455000
b1100 V
b1100 T
b1100 R
b1100 P
b1100000000000000 U
b11000 M
b1100000000000000 S
b11000 K
b1100000000000000 Q
b11000 I
b1100000000000000 O
b11000 G
b1110001011 0
b1110001011 A
b11000101100010000 N
b11000101100010000 L
b11000101100010000 J
b11000101100010000 H
b101010 5
b101010 ;
b101010 X
b110101110 4
b110101110 <
b110111010 F
b110101110 3
b110101110 =
b110111010 E
b110101110 2
b110101110 >
b110111010 D
b11111101 1
b11111101 ?
b1110001011000111011000 B
b100001001 C
0"
1$
#460000
b11000 &
b11000 .
1)
1'
0$
#465000
b1101001 V
b1101001 T
b1101001 R
b1101001 P
b110101110 a
b1110100111 0
b1110100111 A
b1101001100000000000 U
b11010011 M
b1101001100000000000 S
b11010011 K
b1101001100000000000 Q
b11010011 I
b1101001100000000000 O
b11010011 G
b110101110 !
b110101110 8
1"
b110111010 4
b110111010 <
b1000100011 F
b110111010 3
b110111010 =
b1000100011 E
b110111010 2
b110111010 >
b1000100011 D
b100001001 1
b100001001 ?
b1110100111010101011000 B
b101110010 C
b11010011000011011000 N
b11010011000011011000 L
b11010011000011011000 J
b11010011000011011000 H
b101100111 5
b101100111 ;
b101100111 X
1$
#470000
0)
0'
b11100 `
b110101110 [
0$
#475000
b1100001 V
b1100001 T
b1100001 R
b1100001 P
b1100001000000000000 U
b11000010 M
b1100001000000000000 S
b11000010 K
b1100001000000000000 Q
b11000010 I
b1100001000000000000 O
b11000010 G
b10010011110 0
b10010011110 A
b11000010100101111000 N
b11000010100101111000 L
b11000010100101111000 J
b11000010100101111000 H
b101001011 5
b101001011 ;
b101001011 X
b1000100011 4
b1000100011 <
b1010000100 F
b1000100011 3
b1000100011 =
b1010000100 E
b1000100011 2
b1000100011 >
b1010000100 D
b101110010 1
b101110010 ?
b10010011110001111111000 B
b111010011 C
0"
1$
#480000
b11100 &
b11100 .
1)
1'
0$
#485000
b11000 V
b11000 T
b11000 R
b11000 P
b1000100011 a
b10110000010 0
b10110000010 A
b11000100000000000 U
b110001 M
b11000100000000000 S
b110001 K
b11000100000000000 Q
b110001 I
b11000100000000000 O
b110001 G
b1000100011 !
b1000100011 8
1"
b1010000100 4
b1010000100 <
b1010011100 F
b1010000100 3
b1010000100 =
b1010011100 E
b1010000100 2
b1010000100 >
b1010011100 D
b111010011 1
b111010011 ?
b10110000010010110011000 B
b111101011 C
b110001011000100000 N
b110001011000100000 L
b110001011000100000 J
b110001011000100000 H
b1010100 5
b1010100 ;
b1010100 X
1$
#490000
0)
0'
b100000 `
b1000100011 \
0$
#495000
b1111111111010101 V
b1111111111010101 T
b1111111111010101 R
b1111111111010101 P
b11111111111111010101100000000000 U
b1111111110101011 M
b11111111111111010101100000000000 S
b1111111110101011 K
b11111111111111010101100000000000 Q
b1111111110101011 I
b11111111111111010101100000000000 O
b1111111110101011 G
b10110111010 0
b10110111010 A
b11111111111110101011010110000000 N
b11111111111110101011010110000000 L
b11111111111110101011010110000000 J
b11111111111110101011010110000000 H
b1111111101110000 5
b1111111101110000 ;
b1111111101110000 X
b1010011100 4
b1010011100 <
b1001110001 F
b1010011100 3
b1010011100 =
b1001110001 E
b1010011100 2
b1010011100 >
b1001110001 D
b111101011 1
b111101011 ?
b10110111010110010011000 B
b111000000 C
0"
1$
#500000
b100000 &
b100000 .
1)
1'
0$
#505000
b1111111111000101 V
b1111111111000101 T
b1111111111000101 R
b1111111111000101 P
b111101011 a
b10101010101 0
b10101010101 A
b11111111111111000101000000000000 U
b1111111110001010 M
b11111111111111000101000000000000 S
b1111111110001010 K
b11111111111111000101000000000000 Q
b1111111110001010 I
b11111111111111000101000000000000 O
b1111111110001010 G
b111101011 !
b111101011 8
1"
b1001110001 4
b1001110001 <
b1000110110 F
b1001110001 3
b1001110001 =
b1000110110 E
b1001110001 2
b1001110001 >
b1000110110 D
b111000000 1
b111000000 ?
b10101010101101010111000 B
b110000101 C
b11111111111110001010011011000000 N
b11111111111110001010011011000000 L
b11111111111110001010011011000000 J
b11111111111110001010011011000000 H
b1111111100111000 5
b1111111100111000 ;
b1111111100111000 X
1$
#510000
0)
0'
b110011110010 c
b0 b
b11 -
b111101011 ]
0$
#515000
b1111111111100010 V
b1111111111100010 T
b1111111111100010 R
b1111111111100010 P
b11111111111111100010100000000000 U
b1111111111000101 M
b11111111111111100010100000000000 S
b1111111111000101 K
b11111111111111100010100000000000 Q
b1111111111000101 I
b11111111111111100010100000000000 O
b1111111111000101 G
b10011001010 0
b10011001010 A
b11111111111111000101110011001000 N
b11111111111111000101110011001000 L
b11111111111111000101110011001000 J
b11111111111111000101110011001000 H
b1111111110011101 5
b1111111110011101 ;
b1111111110011101 X
b1000110110 4
b1000110110 <
b1000011000 F
b1000110110 3
b1000110110 =
b1000011000 E
b1000110110 2
b1000110110 >
b1000011000 D
b110000101 1
b110000101 ?
b10011001010111011011000 B
b101100111 C
0"
1$
#520000
b110011110010 (
b110011110010 /
b0 &
b0 .
1*
1)
1'
0$
#525000
b1011 V
b1011 T
b1011 R
b1011 P
b10010000100 0
b10010000100 A
b1011100000000000 U
b10111 M
b1011100000000000 S
b10111 K
b1011100000000000 Q
b10111 I
b1011100000000000 O
b10111 G
1#
b110011110010 9
b110011110010 @
1"
b1000011000 4
b1000011000 <
b1000100011 F
b1000011000 3
b1000011000 =
b1000100011 E
b1000011000 2
b1000011000 >
b1000100011 D
b101100111 1
b101100111 ?
b10010000100011000011000 B
b101110010 C
b10111100001000000 N
b10111100001000000 L
b10111100001000000 J
b10111100001000000 H
b101000 5
b101000 ;
b101000 X
1$
#530000
0*
0)
0'
b100101101000 c
b100 b
0$
#535000
b101100 V
b100000 T
b100000 R
b100000 P
b101100000000000000 U
b1011000 M
b100000000000000000 S
b1000000 K
b100000000000000000 Q
b1000000 I
b100000000000000000 O
b1000000 G
b10100010111 0
b10100010111 A
b1011000111111111100 N
b1000000101010110000 L
b1000000101010110000 J
b1000000101010110000 H
b1101110 5
b1101110 ;
b1101110 X
b1000100011 4
b1000100011 <
b1001001111 F
b1000100011 3
b1000100011 =
b1001000011 E
b1000100011 2
b1000100011 >
b1001000011 D
b101110010 1
b101110010 ?
b10100010111001111010110 B
b110010010 C
0#
0"
1$
#540000
b100101101000 (
b100101101000 /
b100 &
b100 .
1*
1)
1'
0$
#545000
b1111111111110001 V
b1111111111110101 R
b1111111111110101 P
b1111111111110001 T
b11111111111111110001000000000000 U
b1111111111100010 M
b11111111111111110101000000000000 Q
b1111111111101010 I
b11111111111111110101000000000000 O
b1111111111101010 G
b10111110011 0
b10111110011 A
b11111111111111110001000000000000 S
b1111111111100010 K
1#
b100101101000 6
b100101101000 :
1"
b1001001111 4
b1001001111 <
b1001000000 F
b1001000011 3
b1001000011 =
b1000110100 E
b1001000011 2
b1001000011 >
b1000111000 D
b110010010 1
b110010010 ?
b110000111 C
b11111111111111100010000100000110 N
b11111111111111101010001111111000 J
b11111111111111101010001111111000 H
b1111111111011011 5
b1111111111011011 ;
b1111111111011011 X
b10111110011010110001100 B
b11111111111111100010000100000110 L
1$
#550000
0*
0)
0'
0$
#555000
b101100110 V
b101100110 T
b101100110 R
b100000100 P
b101100110000000000000 U
b1011001100 M
b101100110000000000000 S
b1011001100 K
b101100110000000000000 Q
b1011001100 I
b100000100000000000000 O
b1000001000 G
b11001001011 0
b11001001011 A
b1011001100000010011010 N
b1011001100000010011010 L
b1011001100000010011010 J
b1000001000010010001000 H
b1101110101 5
b1101110101 ;
b1101110101 X
b1001000000 4
b1001000000 <
b1110100110 F
b1000110100 3
b1000110100 =
b1110011010 E
b1000111000 2
b1000111000 >
b1110011110 D
b110000111 1
b110000111 ?
b11001001011110001110000 B
b1010001011 C
0#
0"
1$
#560000
b1100 &
b1100 .
1)
1'
0$
b1100 `
b11 _
#565000
b101000010 V
b101000010 T
b101000010 R
b101000010 P
b11001001011 a
b101000010000000000000 U
b1010000100 M
b101000010000000000000 S
b1010000100 K
b101000010000000000000 Q
b1010000100 I
b101011011001 0
b101011011001 A
b101000010000000000000 O
b1010000100 G
b11001001011 !
b11001001011 8
1"
b1110100110 4
b1110100110 <
b10011101000 F
b1110011010 3
b1110011010 =
b10011011100 E
b1110011110 2
b1110011110 >
b10011100000 D
b1010001011 1
b1010001011 ?
b1111001101 C
b1010000100110101101010 N
b1010000100110101101010 L
b1010000100110101101010 J
b1100011101 5
b1100011101 ;
b1100011101 X
b101011011001100101000010 B
b1010000100110101101010 H
1$
#570000
0)
0'
b10000 `
b11001001011 ^
0$
#575000
b1111111101101010 V
b1111111101101010 T
b1111111101101010 R
b1111111101101010 P
b11111111111101101010100000000000 U
b1111111011010101 M
b11111111111101101010100000000000 S
b1111111011010101 K
b11111111111101101010100000000000 Q
b1111111011010101 I
b11111111111101101010100000000000 O
b1111111011010101 G
b111011101011 0
b111011101011 A
b11111111111011010101011100101110 N
b11111111111011010101011100101110 L
b11111111111011010101011100101110 J
b11111111111011010101011100101110 H
b1111111010001111 5
b1111111010001111 ;
b1111111010001111 X
b10011101000 4
b10011101000 <
b10001010010 F
b10011011100 3
b10011011100 =
b10001000110 E
b10011100000 2
b10011100000 >
b10001001010 D
b1111001101 1
b1111001101 ?
b111011101011101011010010 B
b1100110111 C
0"
1$
#580000
b10000 &
b10000 .
1)
1'
0$
#585000
b1111110111000101 V
b1111110111000101 T
b1111110111000101 R
b1111110111000101 P
b1111111010001111 a
b110100000110 0
b110100000110 A
b11111111110111000101000000000000 U
b1111101110001010 M
b11111111110111000101000000000000 S
b1111101110001010 K
b11111111110111000101000000000000 Q
b1111101110001010 I
b11111111110111000101000000000000 O
b1111101110001010 G
b1111111010001111 !
b1111111010001111 8
1"
b10001010010 4
b10001010010 <
b1000010111 F
b10001000110 3
b10001000110 =
b1000001011 E
b10001001010 2
b10001001010 >
b1000001111 D
b1100110111 1
b1100110111 ?
b110100000110001110100010 B
b11111100 C
b11111111101110001010011000101010 N
b11111111101110001010011000101010 L
b11111111101110001010011000101010 J
b11111111101110001010011000101010 H
b1111101001111101 5
b1111101001111101 ;
b1111101001111101 X
1$
#590000
0)
0'
b10100 `
b1111111010001111 Y
0$
